{"DispatchLog":[{"CFSID":-4799439,"AdditionalInfo":"","StreetPrefix":"","StreetPreType":"","StreetName":"3","StreetType":"ST","StreetSuffix":"N","VenueName":"FGO","CallType":"Vehicle Break In","NatureOfCall":"VEH BREAK IN RPT","DateString":"4/7/2012 11:59:31 PM","Block":1600,"VenueDescription":"Fargo","IncidentNumber":"","Duration":"1405","Address":"1600 BLK 3 ST N"},{"CFSID":-4799432,"AdditionalInfo":"","StreetPrefix":"","StreetPreType":"","StreetName":"4","StreetType":"ST","StreetSuffix":"N","VenueName":"FGO","CallType":"Impaired Person","NatureOfCall":"TRANSPORT 10-56 F TO DTX","DateString":"4/7/2012 11:52:25 PM","Block":700,"VenueDescription":"Fargo","IncidentNumber":"2012-00020075","Duration":"4078","Address":"700 BLK 4 ST N"},{"CFSID":-4799430,"AdditionalInfo":"","StreetPrefix":"","StreetPreType":"","StreetName":"1","StreetType":"ST","StreetSuffix":"N","VenueName":"FGO","CallType":"Loud Noise","NatureOfCall":"LOUD BAND PLAYING IN GARAGE","DateString":"4/7/2012 11:49:23 PM","Block":500,"VenueDescription":"Fargo","IncidentNumber":"2012-00020071","Duration":"1977","Address":"500 BLK 1 ST N"},{"CFSID":-4799422,"AdditionalInfo":"","StreetPrefix":"","StreetPreType":"","StreetName":"14","StreetType":"AVE","StreetSuffix":"S","VenueName":"FGO","CallType":"Impaired Driver","NatureOfCall":"1055","DateString":"4/7/2012 11:42:27 PM","Block":3400,"VenueDescription":"Fargo","IncidentNumber":"2012-00020062","Duration":"7094","Address":"3400 BLK 14 AVE S"},{"CFSID":-4799397,"AdditionalInfo":"","StreetPrefix":"","StreetPreType":"","StreetName":"22","StreetType":"AVE","StreetSuffix":"S","VenueName":"FGO","CallType":"Gun Shots Heard","NatureOfCall":"HEARD 2 SHOTS","DateString":"4/7/2012 11:11:29 PM","Block":1500,"VenueDescription":"Fargo","IncidentNumber":"2012-00020051","Duration":"482","Address":"1500 BLK 22 AVE S"},{"CFSID":-4799389,"AdditionalInfo":"","StreetPrefix":"","StreetPreType":"","StreetName":"4","StreetType":"AVE","StreetSuffix":"N","VenueName":"FGO","CallType":"Impaired Person","NatureOfCall":"1056 M","DateString":"4/7/2012 11:02:37 PM","Block":0,"VenueDescription":"Fargo","IncidentNumber":"Multiple incidents","Duration":"505","Address":" 4 AVE N"},{"CFSID":-4799379,"AdditionalInfo":"","StreetPrefix":"","StreetPreType":"","StreetName":"10","StreetType":"ST","StreetSuffix":"N","VenueName":"FGO","CallType":"TSI","NatureOfCall":"VIOL PROT ORDER","DateString":"4/7/2012 10:46:26 PM","Block":300,"VenueDescription":"Fargo","IncidentNumber":"2012-00020042","Duration":"5019","Address":"300 BLK 10 ST N"},{"CFSID":-4799376,"AdditionalInfo":"","StreetPrefix":"","StreetPreType":"","StreetName":"4","StreetType":"ST","StreetSuffix":"N","VenueName":"FGO","CallType":"Public Assist","NatureOfCall":"P/U  KIT","DateString":"4/7/2012 10:42:53 PM","Block":700,"VenueDescription":"Fargo","IncidentNumber":"2012-00020050","Duration":"5454","Address":"700 BLK 4 ST N"},{"CFSID":-4799375,"AdditionalInfo":"","StreetPrefix":"","StreetPreType":"","StreetName":"NORTHERN PACIFIC","StreetType":"AVE","StreetSuffix":"N","VenueName":"FGO","CallType":"Impaired Person","NatureOfCall":"1056 M","DateString":"4/7/2012 10:41:27 PM","Block":1000,"VenueDescription":"Fargo","IncidentNumber":"2012-00020041","Duration":"943","Address":"1000 BLK NORTHERN PACIFIC AVE N"},{"CFSID":-4799370,"AdditionalInfo":"","StreetPrefix":"","StreetPreType":"","StreetName":"16","StreetType":"ST","StreetSuffix":"S","VenueName":"FGO","CallType":"Impaired Person","NatureOfCall":"1056 M","DateString":"4/7/2012 10:28:00 PM","Block":100,"VenueDescription":"Fargo","IncidentNumber":"2012-00020037","Duration":"2562","Address":"100 BLK 16 ST S"},{"CFSID":-4799368,"AdditionalInfo":"","StreetPrefix":"","StreetPreType":"","StreetName":"13","StreetType":"AVE","StreetSuffix":"S","VenueName":"FGO","CallType":"Reckless Driving","NatureOfCall":"RECKLESS DRIVING","DateString":"4/7/2012 10:25:56 PM","Block":0,"VenueDescription":"Fargo","IncidentNumber":"2012-00020039","Duration":"684","Address":" 13 AVE S"},{"CFSID":-4799366,"AdditionalInfo":"","StreetPrefix":"","StreetPreType":"","StreetName":"15","StreetType":"ST","StreetSuffix":"S","VenueName":"FGO","CallType":"Domestic","NatureOfCall":"VERBAL DOMESTIC","DateString":"4/7/2012 10:17:28 PM","Block":2600,"VenueDescription":"Fargo","IncidentNumber":"2012-00020035","Duration":"1033","Address":"2600 BLK 15 ST S"},{"CFSID":-4799349,"AdditionalInfo":"","StreetPrefix":"","StreetPreType":"","StreetName":"13","StreetType":"AVE","StreetSuffix":"S","VenueName":"FGO","CallType":"Accident - Property","NatureOfCall":"10-50/P","DateString":"4/7/2012 9:37:14 PM","Block":3900,"VenueDescription":"Fargo","IncidentNumber":"2012-00020031","Duration":"714","Address":"3900 BLK 13 AVE S"},{"CFSID":-4799344,"AdditionalInfo":"","StreetPrefix":"","StreetPreType":"","StreetName":"13 1/2","StreetType":"ST","StreetSuffix":"S","VenueName":"FGO","CallType":"Impaired Person","NatureOfCall":"HELP TRANSPORT 1056 F TO DTX","DateString":"4/7/2012 9:30:00 PM","Block":1800,"VenueDescription":"Fargo","IncidentNumber":"2012-00020030","Duration":"4645","Address":"1800 BLK 13 1/2 ST S"},{"CFSID":-4799343,"AdditionalInfo":"","StreetPrefix":"","StreetPreType":"","StreetName":"31","StreetType":"AVE","StreetSuffix":"S","VenueName":"FGO","CallType":"Disturbance","NatureOfCall":"REMOVE PEOPLE FROM ENTRANCE WAY","DateString":"4/7/2012 9:23:29 PM","Block":3300,"VenueDescription":"Fargo","IncidentNumber":"2012-00020028","Duration":"635","Address":"3300 BLK 31 AVE S"},{"CFSID":-4799342,"AdditionalInfo":"","StreetPrefix":"","StreetPreType":"","StreetName":"25","StreetType":"ST","StreetSuffix":"N","VenueName":"FGO","CallType":"Welfare Check","NatureOfCall":"WELFARE CHECK ON ANIMALS","DateString":"4/7/2012 9:21:55 PM","Block":1000,"VenueDescription":"Fargo","IncidentNumber":"2012-00020029","Duration":"1466","Address":"1000 BLK 25 ST N"},{"CFSID":-4799341,"AdditionalInfo":"","StreetPrefix":"","StreetPreType":"","StreetName":"26 1/2","StreetType":"CT","StreetSuffix":"S","VenueName":"FGO","CallType":"Animal Calls","NatureOfCall":"BARKING DOG","DateString":"4/7/2012 9:19:09 PM","Block":1800,"VenueDescription":"Fargo","IncidentNumber":"2012-00020027","Duration":"2116","Address":"1800 BLK 26 1/2 CT S"},{"CFSID":-4799331,"AdditionalInfo":"","StreetPrefix":"","StreetPreType":"","StreetName":"55","StreetType":"AVE","StreetSuffix":"S","VenueName":"FGO","CallType":"SU","NatureOfCall":"SUSP ACTIVITY","DateString":"4/7/2012 9:02:51 PM","Block":3700,"VenueDescription":"Fargo","IncidentNumber":"2012-00020024","Duration":"471","Address":"3700 BLK 55 AVE S"},{"CFSID":-4799329,"AdditionalInfo":"","StreetPrefix":"","StreetPreType":"","StreetName":"UNIVERSITY","StreetType":"DR","StreetSuffix":"S","VenueName":"FGO","CallType":"Reckless Driving","NatureOfCall":"RECKLESS DRIVERS","DateString":"4/7/2012 9:01:36 PM","Block":1800,"VenueDescription":"Fargo","IncidentNumber":"2012-00020023","Duration":"1098","Address":"1800 BLK UNIVERSITY DR S"},{"CFSID":-4799323,"AdditionalInfo":"","StreetPrefix":"","StreetPreType":"","StreetName":"BROADWAY","StreetType":"","StreetSuffix":"N","VenueName":"FGO","CallType":"Parking Complaint","NatureOfCall":"VEHS BLOCKING SIDEWALK","DateString":"4/7/2012 8:56:03 PM","Block":1400,"VenueDescription":"Fargo","IncidentNumber":"2012-00020033","Duration":"3549","Address":"1400 BLK BROADWAY N"},{"CFSID":-4799319,"AdditionalInfo":"","StreetPrefix":"","StreetPreType":"","StreetName":"10","StreetType":"ST","StreetSuffix":"N","VenueName":"FGO","CallType":"Accident - Injury","NatureOfCall":"VEH VS MAN","DateString":"4/7/2012 8:45:37 PM","Block":300,"VenueDescription":"Fargo","IncidentNumber":"Multiple incidents","Duration":"5375","Address":"300 BLK 10 ST N"},{"CFSID":-4799318,"AdditionalInfo":"","StreetPrefix":"","StreetPreType":"","StreetName":"9","StreetType":"ST","StreetSuffix":"N","VenueName":"FGO","CallType":"Animal Calls","NatureOfCall":"PICK UP DOG","DateString":"4/7/2012 8:44:38 PM","Block":1300,"VenueDescription":"Fargo","IncidentNumber":"Multiple incidents","Duration":"2846","Address":"1300 BLK 9 ST N"},{"CFSID":-4799300,"AdditionalInfo":"","StreetPrefix":"","StreetPreType":"","StreetName":"9","StreetType":"ST","StreetSuffix":"N","VenueName":"FGO","CallType":"Animal Calls","NatureOfCall":"DOG AT LARGE","DateString":"4/7/2012 8:00:51 PM","Block":1300,"VenueDescription":"Fargo","IncidentNumber":"","Duration":"2726","Address":"1300 BLK 9 ST N"},{"CFSID":-4799297,"AdditionalInfo":"","StreetPrefix":"","StreetPreType":"","StreetName":"UNIVERSITY","StreetType":"DR","StreetSuffix":"N","VenueName":"FGO","CallType":"Disturbance","NatureOfCall":"DISTURBANCE","DateString":"4/7/2012 7:51:51 PM","Block":1100,"VenueDescription":"Fargo","IncidentNumber":"2012-00020012","Duration":"1375","Address":"1100 BLK UNIVERSITY DR N"},{"CFSID":-4799295,"AdditionalInfo":"","StreetPrefix":"","StreetPreType":"","StreetName":"COUNTRYSIDE TRAILER","StreetType":"CT","StreetSuffix":"S","VenueName":"FGO","CallType":"Reckless Driving","NatureOfCall":"RECKLESS DRIVER ","DateString":"4/7/2012 7:50:07 PM","Block":700,"VenueDescription":"Fargo","IncidentNumber":"2012-00020014","Duration":"374","Address":"700 BLK COUNTRYSIDE TRAILER CT S"},{"CFSID":-4799292,"AdditionalInfo":"","StreetPrefix":"","StreetPreType":"","StreetName":"NORTHERN PACIFIC","StreetType":"AVE","StreetSuffix":"N","VenueName":"FGO","CallType":"Impaired Person","NatureOfCall":"1056 M NEEDS TRNSFR TO DTX","DateString":"4/7/2012 7:47:33 PM","Block":500,"VenueDescription":"Fargo","IncidentNumber":"Multiple incidents","Duration":"3486","Address":"500 BLK NORTHERN PACIFIC AVE N"},{"CFSID":-4799286,"AdditionalInfo":"","StreetPrefix":"","StreetPreType":"","StreetName":"10","StreetType":"AVE","StreetSuffix":"S","VenueName":"FGO","CallType":"SU","NatureOfCall":"SUSP VEH","DateString":"4/7/2012 7:39:55 PM","Block":4300,"VenueDescription":"Fargo","IncidentNumber":"2012-00020011","Duration":"409","Address":"4300 BLK 10 AVE S"},{"CFSID":-4799285,"AdditionalInfo":"","StreetPrefix":"","StreetPreType":"","StreetName":"19","StreetType":"AVE","StreetSuffix":"S","VenueName":"FGO","CallType":"Impaired Driver","NatureOfCall":"1055","DateString":"4/7/2012 7:39:46 PM","Block":4500,"VenueDescription":"Fargo","IncidentNumber":"2012-00020010","Duration":"4516","Address":"4500 BLK 19 AVE S"},{"CFSID":-4799282,"AdditionalInfo":"","StreetPrefix":"","StreetPreType":"","StreetName":"UNIVERSITY VILLAGE","StreetType":"","StreetSuffix":"N","VenueName":"FGO","CallType":"Theft","NatureOfCall":"THEFT OF LIC PLATE","DateString":"4/7/2012 7:18:05 PM","Block":100,"VenueDescription":"Fargo","IncidentNumber":"2012-00003022","Duration":"1903","Address":"100 BLK UNIVERSITY VILLAGE N"},{"CFSID":-4799281,"AdditionalInfo":"","StreetPrefix":"","StreetPreType":"","StreetName":"1","StreetType":"AVE","StreetSuffix":"S","VenueName":"FGO","CallType":"Impaired Person","NatureOfCall":"1056 M NEEDS TRNSFR TO DTX","DateString":"4/7/2012 7:15:39 PM","Block":1500,"VenueDescription":"Fargo","IncidentNumber":"2012-00020009","Duration":"1207","Address":"1500 BLK 1 AVE S"},{"CFSID":-4799278,"AdditionalInfo":"","StreetPrefix":"","StreetPreType":"","StreetName":"UNIVERSITY VILLAGE","StreetType":"","StreetSuffix":"N","VenueName":"FGO","CallType":"Theft","NatureOfCall":"STOLEN LICENSE PLATE","DateString":"4/7/2012 7:09:37 PM","Block":100,"VenueDescription":"Fargo","IncidentNumber":"","Duration":"409","Address":"100 BLK UNIVERSITY VILLAGE N"},{"CFSID":-4799276,"AdditionalInfo":"","StreetPrefix":"","StreetPreType":"","StreetName":"34","StreetType":"AVE","StreetSuffix":"S","VenueName":"FGO","CallType":"Vehicle Break In","NatureOfCall":"VEH BREAK IN REPORT","DateString":"4/7/2012 7:02:51 PM","Block":4300,"VenueDescription":"Fargo","IncidentNumber":"2012-00020007","Duration":"1273","Address":"4300 BLK 34 AVE S"},{"CFSID":-4799264,"AdditionalInfo":"","StreetPrefix":"","StreetPreType":"","StreetName":"14","StreetType":"ST","StreetSuffix":"S","VenueName":"FGO","CallType":"Parking Complaint","NatureOfCall":"ABANDON VEH","DateString":"4/7/2012 6:28:55 PM","Block":6100,"VenueDescription":"Fargo","IncidentNumber":"2012-00020004","Duration":"2448","Address":"6100 BLK 14 ST S"},{"CFSID":-4799263,"AdditionalInfo":"","StreetPrefix":"","StreetPreType":"","StreetName":"21","StreetType":"ST","StreetSuffix":"S","VenueName":"FGO","CallType":"Suicidal Person","NatureOfCall":"SUICIDAL F","DateString":"4/7/2012 6:25:36 PM","Block":100,"VenueDescription":"Fargo","IncidentNumber":"Multiple incidents","Duration":"4747","Address":"100 BLK 21 ST S"},{"CFSID":-4799257,"AdditionalInfo":"","StreetPrefix":"E","StreetPreType":"","StreetName":"GATEWAY","StreetType":"CIR","StreetSuffix":"S","VenueName":"FGO","CallType":"SU","NatureOfCall":"NEIGHBORS HAVE AN OPEN DOOR","DateString":"4/7/2012 6:07:16 PM","Block":1500,"VenueDescription":"Fargo","IncidentNumber":"2012-00020001","Duration":"1932","Address":"1500 BLK E GATEWAY CIR S"},{"CFSID":-4799248,"AdditionalInfo":"","StreetPrefix":"","StreetPreType":"","StreetName":"4","StreetType":"ST","StreetSuffix":"N","VenueName":"FGO","CallType":"Welfare Check","NatureOfCall":"WELFARE CHECK/JUVS LEFT IN VEH","DateString":"4/7/2012 5:31:21 PM","Block":700,"VenueDescription":"Fargo","IncidentNumber":"2012-00019999","Duration":"2281","Address":"700 BLK 4 ST N"},{"CFSID":-4799246,"AdditionalInfo":"","StreetPrefix":"","StreetPreType":"","StreetName":"18","StreetType":"ST","StreetSuffix":"S","VenueName":"FGO","CallType":"Accident - Property","NatureOfCall":"1050P H&R","DateString":"4/7/2012 5:24:39 PM","Block":0,"VenueDescription":"Fargo","IncidentNumber":"2012-00019996","Duration":"3599","Address":"0 BLK 18 ST S"},{"CFSID":-4799240,"AdditionalInfo":"","StreetPrefix":"","StreetPreType":"","StreetName":"VILLA","StreetType":"DR","StreetSuffix":"S","VenueName":"FGO","CallType":"Welfare Check","NatureOfCall":"WELFARE CHECK/MEDICAL ASSIST?","DateString":"4/7/2012 5:15:36 PM","Block":2500,"VenueDescription":"Fargo","IncidentNumber":"2012-00019995","Duration":"815","Address":"2500 BLK VILLA DR S"},{"CFSID":-4799235,"AdditionalInfo":"","StreetPrefix":"","StreetPreType":"","StreetName":"21","StreetType":"ST","StreetSuffix":"S","VenueName":"FGO","CallType":"Accident - Property","NatureOfCall":"1050P REPORT","DateString":"4/7/2012 4:56:42 PM","Block":700,"VenueDescription":"Fargo","IncidentNumber":"2012-00019992","Duration":"2194","Address":"700 BLK 21 ST S"},{"CFSID":-4799234,"AdditionalInfo":"","StreetPrefix":"","StreetPreType":"","StreetName":"","StreetType":"","StreetSuffix":"","VenueName":"FGO","CallType":"Test","NatureOfCall":"TEST CALL","DateString":"4/7/2012 4:55:18 PM","Block":0,"VenueDescription":"Fargo","IncidentNumber":"","Duration":"59","Address":""},{"CFSID":-4799233,"AdditionalInfo":"","StreetPrefix":"","StreetPreType":"","StreetName":"9","StreetType":"ST","StreetSuffix":"S","VenueName":"FGO","CallType":"Missing Person","NatureOfCall":"MISSING PERSON REPORT","DateString":"4/7/2012 4:54:55 PM","Block":1300,"VenueDescription":"Fargo","IncidentNumber":"2012-00019993","Duration":"4486","Address":"1300 BLK 9 ST S"},{"CFSID":-4799232,"AdditionalInfo":"","StreetPrefix":"","StreetPreType":"","StreetName":"12","StreetType":"AVE","StreetSuffix":"N","VenueName":"FGO","CallType":"Bon Fire","NatureOfCall":"BON FIRE","DateString":"4/7/2012 4:51:27 PM","Block":0,"VenueDescription":"Fargo","IncidentNumber":"Multiple incidents","Duration":"3028","Address":"0 BLK 12 AVE N"},{"CFSID":-4799227,"AdditionalInfo":"","StreetPrefix":"","StreetPreType":"","StreetName":"1","StreetType":"AVE","StreetSuffix":"S","VenueName":"FGO","CallType":"Found Property","NatureOfCall":"FOUND DEBIT CARD","DateString":"4/7/2012 4:41:10 PM","Block":1400,"VenueDescription":"Fargo","IncidentNumber":"2012-00019991","Duration":"925","Address":"1400 BLK 1 AVE S"},{"CFSID":-4799226,"AdditionalInfo":"","StreetPrefix":"","StreetPreType":"","StreetName":"4","StreetType":"ST","StreetSuffix":"N","VenueName":"FGO","CallType":"Impaired Person","NatureOfCall":"TRANSPORT 1056M TO DTX","DateString":"4/7/2012 4:38:49 PM","Block":700,"VenueDescription":"Fargo","IncidentNumber":"Multiple incidents","Duration":"3097","Address":"700 BLK 4 ST N"},{"CFSID":-4799214,"AdditionalInfo":"","StreetPrefix":"","StreetPreType":"","StreetName":"19","StreetType":"AVE","StreetSuffix":"N","VenueName":"FGO","CallType":"Theft","NatureOfCall":"THEFT OF MONEY","DateString":"4/7/2012 4:23:50 PM","Block":1100,"VenueDescription":"Fargo","IncidentNumber":"2012-00019998","Duration":"7258","Address":"1100 BLK 19 AVE N"},{"CFSID":-4799212,"AdditionalInfo":"","StreetPrefix":"","StreetPreType":"","StreetName":"19","StreetType":"AVE","StreetSuffix":"N","VenueName":"FGO","CallType":"ATL Wanted","NatureOfCall":"ATL MISSING PERSON","DateString":"4/7/2012 4:21:25 PM","Block":0,"VenueDescription":"Fargo","IncidentNumber":"Multiple incidents","Duration":"2916","Address":" 19 AVE N"},{"CFSID":-4799210,"AdditionalInfo":"","StreetPrefix":"","StreetPreType":"","StreetName":"BROADWAY","StreetType":"","StreetSuffix":"N","VenueName":"FGO","CallType":"Medical-C ","NatureOfCall":"58 YOA M","DateString":"4/7/2012 4:06:04 PM","Block":300,"VenueDescription":"Fargo","IncidentNumber":"Multiple incidents","Duration":"1108","Address":"300 BLK BROADWAY N"},{"CFSID":-4799207,"AdditionalInfo":"","StreetPrefix":"","StreetPreType":"","StreetName":"8","StreetType":"AVE","StreetSuffix":"N","VenueName":"FGO","CallType":"Theft","NatureOfCall":"THEFT REPORT","DateString":"4/7/2012 3:57:44 PM","Block":700,"VenueDescription":"Fargo","IncidentNumber":"2012-00019997","Duration":"9810","Address":"700 BLK 8 AVE N"},{"CFSID":-4799206,"AdditionalInfo":"","StreetPrefix":"","StreetPreType":"","StreetName":"CENTENNIAL","StreetType":"BLVD","StreetSuffix":"N","VenueName":"FGO","CallType":"Suspicious Package/Powder/Letter","NatureOfCall":"SU LETTER","DateString":"4/7/2012 3:50:12 PM","Block":1700,"VenueDescription":"Fargo","IncidentNumber":"2012-00003020","Duration":"1331","Address":"1700 BLK CENTENNIAL BLVD N"},{"CFSID":-4799199,"AdditionalInfo":"","StreetPrefix":"","StreetPreType":"","StreetName":"3","StreetType":"AVE","StreetSuffix":"N","VenueName":"FGO","CallType":"Disturbance","NatureOfCall":"DISTURBANCE","DateString":"4/7/2012 3:29:22 PM","Block":500,"VenueDescription":"Fargo","IncidentNumber":"","Duration":"162","Address":"500 BLK 3 AVE N"},{"CFSID":-4799197,"AdditionalInfo":"","StreetPrefix":"","StreetPreType":"","StreetName":"3","StreetType":"AVE","StreetSuffix":"N","VenueName":"FGO","CallType":"Assault","NatureOfCall":"JUST HPND\r\n","DateString":"4/7/2012 3:29:01 PM","Block":500,"VenueDescription":"Fargo","IncidentNumber":"Multiple incidents","Duration":"4285","Address":"500 BLK 3 AVE N"},{"CFSID":-4799193,"AdditionalInfo":"","StreetPrefix":"","StreetPreType":"","StreetName":"4","StreetType":"ST","StreetSuffix":"N","VenueName":"FGO","CallType":"Missing Person","NatureOfCall":"MISSING PERSON RPT","DateString":"4/7/2012 3:21:19 PM","Block":200,"VenueDescription":"Fargo","IncidentNumber":"2012-00019988","Duration":"3130","Address":"200 BLK 4 ST N"},{"CFSID":-4799192,"AdditionalInfo":"","StreetPrefix":"","StreetPreType":"","StreetName":"4","StreetType":"ST","StreetSuffix":"N","VenueName":"FGO","CallType":"Sexual Assault","NatureOfCall":"SEXUALT ASSAULT","DateString":"4/7/2012 3:19:29 PM","Block":700,"VenueDescription":"Fargo","IncidentNumber":"2012-00019986","Duration":"24332","Address":"700 BLK 4 ST N"},{"CFSID":-4799186,"AdditionalInfo":"","StreetPrefix":"","StreetPreType":"","StreetName":"MAIN","StreetType":"AVE","StreetSuffix":"","VenueName":"FGO","CallType":"ATL Wanted","NatureOfCall":"CRIMINALLY TRESPASS M","DateString":"4/7/2012 2:55:11 PM","Block":300,"VenueDescription":"Fargo","IncidentNumber":"2012-00019985","Duration":"10277","Address":"300 BLK MAIN AVE"},{"CFSID":-4799185,"AdditionalInfo":"","StreetPrefix":"","StreetPreType":"","StreetName":"COUNTRYSIDE TRAILER","StreetType":"CT","StreetSuffix":"S","VenueName":"FGO","CallType":"Disturbance","NatureOfCall":"VERBAL","DateString":"4/7/2012 2:51:27 PM","Block":700,"VenueDescription":"Fargo","IncidentNumber":"2012-00019984","Duration":"645","Address":"700 BLK COUNTRYSIDE TRAILER CT S"},{"CFSID":-4799183,"AdditionalInfo":"","StreetPrefix":"","StreetPreType":"","StreetName":"CENTENNIAL","StreetType":"BLVD","StreetSuffix":"N","VenueName":"FGO","CallType":"Disturbance","NatureOfCall":"VERB DISTURBANCE AT FRONT DESK\r\n","DateString":"4/7/2012 2:47:57 PM","Block":1700,"VenueDescription":"Fargo","IncidentNumber":"2012-00003019","Duration":"1691","Address":"1700 BLK CENTENNIAL BLVD N"},{"CFSID":-4799180,"AdditionalInfo":"","StreetPrefix":"","StreetPreType":"","StreetName":"8","StreetType":"AVE","StreetSuffix":"N","VenueName":"FGO","CallType":"Public Assist","NatureOfCall":"CIVIL ?S 1021 ONLY","DateString":"4/7/2012 2:43:24 PM","Block":700,"VenueDescription":"Fargo","IncidentNumber":"2012-00019983","Duration":"2484","Address":"700 BLK 8 AVE N"},{"CFSID":-4799177,"AdditionalInfo":"","StreetPrefix":"","StreetPreType":"","StreetName":"FILLMORE","StreetType":"ST","StreetSuffix":"S","VenueName":"FGO","CallType":"Vehicle Break In","NatureOfCall":"VEH BREAK IN 1021 ONLY","DateString":"4/7/2012 2:33:47 PM","Block":3600,"VenueDescription":"Fargo","IncidentNumber":"2012-00019982","Duration":"1526","Address":"3600 BLK FILLMORE ST S"},{"CFSID":-4799174,"AdditionalInfo":"","StreetPrefix":"","StreetPreType":"","StreetName":"14","StreetType":"ST","StreetSuffix":"S","VenueName":"FGO","CallType":"Disturbance","NatureOfCall":"VERBAL","DateString":"4/7/2012 2:25:08 PM","Block":2500,"VenueDescription":"Fargo","IncidentNumber":"2012-00019981","Duration":"1369","Address":"2500 BLK 14 ST S"},{"CFSID":-4799170,"AdditionalInfo":"","StreetPrefix":"","StreetPreType":"","StreetName":"2","StreetType":"ST","StreetSuffix":"N","VenueName":"FGO","CallType":"Disturbance","NatureOfCall":"UNWANTED M","DateString":"4/7/2012 2:16:59 PM","Block":1700,"VenueDescription":"Fargo","IncidentNumber":"2012-00019980","Duration":"1169","Address":"1700 BLK 2 ST N"},{"CFSID":-4799167,"AdditionalInfo":"","StreetPrefix":"","StreetPreType":"","StreetName":"4","StreetType":"ST","StreetSuffix":"N","VenueName":"FGO","CallType":"Public Assist","NatureOfCall":"QUESTIONS FOR OFFCR","DateString":"4/7/2012 2:08:49 PM","Block":200,"VenueDescription":"Fargo","IncidentNumber":"2012-00019979","Duration":"1298","Address":"200 BLK 4 ST N"},{"CFSID":-4799158,"AdditionalInfo":"","StreetPrefix":"","StreetPreType":"","StreetName":"13","StreetType":"AVE","StreetSuffix":"S","VenueName":"FGO","CallType":"Shoplifting","NatureOfCall":"A/F/SHOPLIFTER/COOPERATIVE","DateString":"4/7/2012 1:36:12 PM","Block":4700,"VenueDescription":"Fargo","IncidentNumber":"2012-00019974","Duration":"3139","Address":"4700 BLK 13 AVE S"},{"CFSID":-4799156,"AdditionalInfo":"","StreetPrefix":"","StreetPreType":"","StreetName":"45","StreetType":"ST","StreetSuffix":"N","VenueName":"FGO","CallType":"Suicidal Person","NatureOfCall":"SUICIDAL F","DateString":"4/7/2012 1:29:23 PM","Block":4000,"VenueDescription":"Fargo","IncidentNumber":"2012-00006013","Duration":"2388","Address":"4000 BLK 45 ST N"},{"CFSID":-4799153,"AdditionalInfo":"","StreetPrefix":"","StreetPreType":"","StreetName":"25","StreetType":"ST","StreetSuffix":"S","VenueName":"FGO","CallType":"Impaired Driver","NatureOfCall":"1055","DateString":"4/7/2012 1:19:37 PM","Block":3100,"VenueDescription":"Fargo","IncidentNumber":"2012-00019973","Duration":"488","Address":"3100 BLK 25 ST S"},{"CFSID":-4799151,"AdditionalInfo":"","StreetPrefix":"","StreetPreType":"","StreetName":"14","StreetType":"ST","StreetSuffix":"S","VenueName":"FGO","CallType":"Animal Calls","NatureOfCall":"DOG AT LARGE","DateString":"4/7/2012 1:16:43 PM","Block":1700,"VenueDescription":"Fargo","IncidentNumber":"2012-00019975","Duration":"2018","Address":"1700 BLK 14 ST S"},{"CFSID":-4799148,"AdditionalInfo":"","StreetPrefix":"","StreetPreType":"","StreetName":"EAST ROSE CREEK","StreetType":"PKWY","StreetSuffix":"S","VenueName":"FGO","CallType":"Vehicle Break In","NatureOfCall":"VEH BREAK IN X2/WILL BE THERE AT 1320","DateString":"4/7/2012 12:56:04 PM","Block":1900,"VenueDescription":"Fargo","IncidentNumber":"2012-00019970","Duration":"6456","Address":"1900 BLK EAST ROSE CREEK PKWY S"},{"CFSID":-4799147,"AdditionalInfo":"","StreetPrefix":"","StreetPreType":"","StreetName":"12","StreetType":"ST","StreetSuffix":"N","VenueName":"FGO","CallType":"Animal Calls","NatureOfCall":"ANIMAL CALL","DateString":"4/7/2012 12:53:27 PM","Block":1400,"VenueDescription":"Fargo","IncidentNumber":"2012-00019972","Duration":"2735","Address":"1400 BLK 12 ST N"},{"CFSID":-4799145,"AdditionalInfo":"","StreetPrefix":"","StreetPreType":"","StreetName":"9","StreetType":"ST","StreetSuffix":"N","VenueName":"FGO","CallType":"Bicycle - Found","NatureOfCall":"PICK UP FOUND BIKE","DateString":"4/7/2012 12:40:35 PM","Block":700,"VenueDescription":"Fargo","IncidentNumber":"2012-00019969","Duration":"1989","Address":"700 BLK 9 ST N"},{"CFSID":-4799140,"AdditionalInfo":"","StreetPrefix":"","StreetPreType":"","StreetName":"4","StreetType":"ST","StreetSuffix":"N","VenueName":"FGO","CallType":"Stolen Vehicle","NatureOfCall":"STOLEN VEH","DateString":"4/7/2012 12:26:22 PM","Block":1000,"VenueDescription":"Fargo","IncidentNumber":"2012-00019971","Duration":"3109","Address":"1000 BLK 4 ST N"},{"CFSID":-4799138,"AdditionalInfo":"","StreetPrefix":"","StreetPreType":"","StreetName":"19","StreetType":"AVE","StreetSuffix":"S","VenueName":"FGO","CallType":"911 Hang Up Public Place","NatureOfCall":"911 HANG UP","DateString":"4/7/2012 12:19:00 PM","Block":4700,"VenueDescription":"Fargo","IncidentNumber":"2012-00019967","Duration":"2922","Address":"4700 BLK 19 AVE S"},{"CFSID":-4799132,"AdditionalInfo":"","StreetPrefix":"","StreetPreType":"","StreetName":"7","StreetType":"AVE","StreetSuffix":"N","VenueName":"FGO","CallType":"Impaired Person","NatureOfCall":"1056 M","DateString":"4/7/2012 12:10:06 PM","Block":0,"VenueDescription":"Fargo","IncidentNumber":"","Duration":"213","Address":" 7 AVE N"},{"CFSID":-4799134,"AdditionalInfo":"","StreetPrefix":"","StreetPreType":"","StreetName":"7","StreetType":"AVE","StreetSuffix":"N","VenueName":"FGO","CallType":"Impaired Person","NatureOfCall":"CHECK ON POSS 1056/M","DateString":"4/7/2012 12:10:00 PM","Block":200,"VenueDescription":"Fargo","IncidentNumber":"2012-00019968","Duration":"2975","Address":"200 BLK 7 AVE N"},{"CFSID":-4799129,"AdditionalInfo":"","StreetPrefix":"","StreetPreType":"","StreetName":"UNIVERSITY","StreetType":"DR","StreetSuffix":"S","VenueName":"FGO","CallType":"Disturbance","NatureOfCall":"DISTURBANCE","DateString":"4/7/2012 12:04:02 PM","Block":1400,"VenueDescription":"Fargo","IncidentNumber":"2012-00019966","Duration":"4088","Address":"1400 BLK UNIVERSITY DR S"},{"CFSID":-4799127,"AdditionalInfo":"","StreetPrefix":"W ","StreetPreType":"","StreetName":"GATEWAY","StreetType":"CIR","StreetSuffix":"S","VenueName":"FGO","CallType":"Medical-C ","NatureOfCall":"88 YOA/M W/ HIGH BP","DateString":"4/7/2012 11:56:00 AM","Block":1400,"VenueDescription":"Fargo","IncidentNumber":"Multiple incidents","Duration":"3636","Address":"1400 BLK W  GATEWAY CIR S"},{"CFSID":-4799122,"AdditionalInfo":"","StreetPrefix":"","StreetPreType":"","StreetName":"VILLA","StreetType":"DR","StreetSuffix":"S","VenueName":"FGO","CallType":"Impaired Person","NatureOfCall":"1056/ MEDICAL ASSIST?","DateString":"4/7/2012 11:50:54 AM","Block":2500,"VenueDescription":"Fargo","IncidentNumber":"Multiple incidents","Duration":"1746","Address":"2500 BLK VILLA DR S"},{"CFSID":-4799121,"AdditionalInfo":"","StreetPrefix":"","StreetPreType":"","StreetName":"16","StreetType":"ST","StreetSuffix":"N","VenueName":"FGO","CallType":"Welfare Check","NatureOfCall":"WELFARE CHK 1096 F","DateString":"4/7/2012 11:50:02 AM","Block":1000,"VenueDescription":"Fargo","IncidentNumber":"2012-00019965","Duration":"2399","Address":"1000 BLK 16 ST N"},{"CFSID":-4799117,"AdditionalInfo":"","StreetPrefix":"","StreetPreType":"","StreetName":"33","StreetType":"AVE","StreetSuffix":"S","VenueName":"FGO","CallType":"Vehicle Break In","NatureOfCall":"VEH BREAK IN ","DateString":"4/7/2012 11:39:40 AM","Block":4200,"VenueDescription":"Fargo","IncidentNumber":"2012-00019961","Duration":"8626","Address":"4200 BLK 33 AVE S"},{"CFSID":-4799116,"AdditionalInfo":"","StreetPrefix":"","StreetPreType":"","StreetName":"4","StreetType":"ST","StreetSuffix":"N","VenueName":"FGO","CallType":"Vehicle Break In","NatureOfCall":"VEH BREAK IN","DateString":"4/7/2012 11:34:13 AM","Block":200,"VenueDescription":"Fargo","IncidentNumber":"2012-00019960","Duration":"1918","Address":"200 BLK 4 ST N"},{"CFSID":-4799114,"AdditionalInfo":"","StreetPrefix":"","StreetPreType":"","StreetName":"11","StreetType":"ST","StreetSuffix":"N","VenueName":"FGO","CallType":"Disturbance","NatureOfCall":"DISTURBANCE","DateString":"4/7/2012 11:29:30 AM","Block":400,"VenueDescription":"Fargo","IncidentNumber":"2012-00019959","Duration":"684","Address":"400 BLK 11 ST N"},{"CFSID":-4799113,"AdditionalInfo":"","StreetPrefix":"","StreetPreType":"","StreetName":"35","StreetType":"ST","StreetSuffix":"S","VenueName":"FGO","CallType":"Disturbance","NatureOfCall":"AGRESSIVE FORMER EMPLOYEE","DateString":"4/7/2012 11:27:00 AM","Block":1400,"VenueDescription":"Fargo","IncidentNumber":"2012-00019958","Duration":"6018","Address":"1400 BLK 35 ST S"},{"CFSID":-4799104,"AdditionalInfo":"","StreetPrefix":"","StreetPreType":"","StreetName":"PIERCE","StreetType":"ST","StreetSuffix":"S","VenueName":"FGO","CallType":"Vehicle Break In","NatureOfCall":"VEH BREAK IN/1021 ONLY","DateString":"4/7/2012 10:58:55 AM","Block":3600,"VenueDescription":"Fargo","IncidentNumber":"2012-00019955","Duration":"1676","Address":"3600 BLK PIERCE ST S"},{"CFSID":-4799103,"AdditionalInfo":"","StreetPrefix":"","StreetPreType":"","StreetName":"NORTHERN PACIFIC","StreetType":"AVE","StreetSuffix":"N","VenueName":"FGO","CallType":"Impaired Person","NatureOfCall":"1056 NA/F","DateString":"4/7/2012 10:55:46 AM","Block":500,"VenueDescription":"Fargo","IncidentNumber":"2012-00019953","Duration":"1886","Address":"500 BLK NORTHERN PACIFIC AVE N"},{"CFSID":-4799102,"AdditionalInfo":"","StreetPrefix":"","StreetPreType":"","StreetName":"1","StreetType":"AVE","StreetSuffix":"S","VenueName":"FGO","CallType":"Missing Person","NatureOfCall":"MISSING PSZHICHOPHRENIC 39 YOA F","DateString":"4/7/2012 10:54:24 AM","Block":400,"VenueDescription":"Fargo","IncidentNumber":"2012-00019954","Duration":"1858","Address":"400 BLK 1 AVE S"},{"CFSID":-4799091,"AdditionalInfo":"","StreetPrefix":"","StreetPreType":"","StreetName":"UNIVERSITY","StreetType":"DR","StreetSuffix":"S","VenueName":"FGO","CallType":"Accident - Property","NatureOfCall":"1050H&R","DateString":"4/7/2012 10:24:05 AM","Block":0,"VenueDescription":"Fargo","IncidentNumber":"2012-00019951","Duration":"3709","Address":" UNIVERSITY DR S"},{"CFSID":-4799090,"AdditionalInfo":"","StreetPrefix":"","StreetPreType":"","StreetName":"1","StreetType":"AVE","StreetSuffix":"S","VenueName":"FGO","CallType":"Disturbance","NatureOfCall":"1056 M WANTS TO GO TO JAIL","DateString":"4/7/2012 10:23:12 AM","Block":1500,"VenueDescription":"Fargo","IncidentNumber":"2012-00019949","Duration":"1315","Address":"1500 BLK 1 AVE S"},{"CFSID":-4799083,"AdditionalInfo":"","StreetPrefix":"S ","StreetPreType":"","StreetName":"TERRACE","StreetType":"","StreetSuffix":"N","VenueName":"FGO","CallType":"Animal Calls","NatureOfCall":"DOG AT LARGE","DateString":"4/7/2012 9:58:32 AM","Block":0,"VenueDescription":"Fargo","IncidentNumber":"","Duration":"58","Address":"0 BLK S  TERRACE N"},{"CFSID":-4799077,"AdditionalInfo":"","StreetPrefix":"","StreetPreType":"","StreetName":"BROADWAY","StreetType":"","StreetSuffix":"N","VenueName":"FGO","CallType":"Alarm","NatureOfCall":"1090 ","DateString":"4/7/2012 9:19:34 AM","Block":200,"VenueDescription":"Fargo","IncidentNumber":"2012-00019947","Duration":"281","Address":"200 BLK BROADWAY N"},{"CFSID":-4799072,"AdditionalInfo":"","StreetPrefix":"","StreetPreType":"","StreetName":"4","StreetType":"ST","StreetSuffix":"N","VenueName":"FGO","CallType":"Found Property","NatureOfCall":"HERE TO PICKUP FOUND WALLET","DateString":"4/7/2012 8:51:42 AM","Block":200,"VenueDescription":"Fargo","IncidentNumber":"2012-00019945","Duration":"1192","Address":"200 BLK 4 ST N"},{"CFSID":-4799070,"AdditionalInfo":"","StreetPrefix":"","StreetPreType":"","StreetName":"UNIVERSITY","StreetType":"DR","StreetSuffix":"S","VenueName":"FGO","CallType":"Medical-C ","NatureOfCall":"MEDICAL","DateString":"4/7/2012 8:45:21 AM","Block":200,"VenueDescription":"Fargo","IncidentNumber":"Multiple incidents","Duration":"1582","Address":"200 BLK UNIVERSITY DR S"},{"CFSID":-4799066,"AdditionalInfo":"","StreetPrefix":"","StreetPreType":"","StreetName":"MONROE","StreetType":"ST","StreetSuffix":"S","VenueName":"FGO","CallType":"Vehicle Break In","NatureOfCall":"VEH BREAK IN X2","DateString":"4/7/2012 8:29:51 AM","Block":3300,"VenueDescription":"Fargo","IncidentNumber":"2012-00019942","Duration":"1799","Address":"3300 BLK MONROE ST S"},{"CFSID":-4799065,"AdditionalInfo":"","StreetPrefix":"","StreetPreType":"","StreetName":"16","StreetType":"ST","StreetSuffix":"S","VenueName":"FGO","CallType":"SU","NatureOfCall":"SUSP MALE","DateString":"4/7/2012 8:28:41 AM","Block":300,"VenueDescription":"Fargo","IncidentNumber":"2012-00019941","Duration":"758","Address":"300 BLK 16 ST S"},{"CFSID":-4799064,"AdditionalInfo":"","StreetPrefix":"","StreetPreType":"","StreetName":"2","StreetType":"AVE","StreetSuffix":"N","VenueName":"FGO","CallType":"TC","NatureOfCall":"CHECK ON LIGHTS MALFUNCTIONING","DateString":"4/7/2012 8:28:20 AM","Block":0,"VenueDescription":"Fargo","IncidentNumber":"2012-00019943","Duration":"882","Address":" 2 AVE N"},{"CFSID":-4799062,"AdditionalInfo":"","StreetPrefix":"","StreetPreType":"","StreetName":"2","StreetType":"ST","StreetSuffix":"N","VenueName":"FGO","CallType":"Animal Calls","NatureOfCall":"FOUND BLK LAB","DateString":"4/7/2012 8:14:56 AM","Block":1200,"VenueDescription":"Fargo","IncidentNumber":"2012-00019948","Duration":"6592","Address":"1200 BLK 2 ST N"},{"CFSID":-4799061,"AdditionalInfo":"","StreetPrefix":"","StreetPreType":"","StreetName":"14","StreetType":"AVE","StreetSuffix":"S","VenueName":"FGO","CallType":"Theft","NatureOfCall":"THEFT OF PURSE/1021 ONLY","DateString":"4/7/2012 8:14:43 AM","Block":5100,"VenueDescription":"Fargo","IncidentNumber":"2012-00019940","Duration":"1130","Address":"5100 BLK 14 AVE S"},{"CFSID":-4799059,"AdditionalInfo":"","StreetPrefix":"","StreetPreType":"","StreetName":"10","StreetType":"AVE","StreetSuffix":"S","VenueName":"FGO","CallType":"Animal Calls","NatureOfCall":"ANIMAL COMPL","DateString":"4/7/2012 8:06:31 AM","Block":4200,"VenueDescription":"Fargo","IncidentNumber":"2012-00019946","Duration":"10261","Address":"4200 BLK 10 AVE S"},{"CFSID":-4799056,"AdditionalInfo":"","StreetPrefix":"","StreetPreType":"","StreetName":"PIERCE","StreetType":"ST","StreetSuffix":"S","VenueName":"FGO","CallType":"Theft","NatureOfCall":"THEFT FROM GARAGE","DateString":"4/7/2012 7:55:18 AM","Block":3600,"VenueDescription":"Fargo","IncidentNumber":"2012-00019939","Duration":"10947","Address":"3600 BLK PIERCE ST S"},{"CFSID":-4799055,"AdditionalInfo":"1/2","StreetPrefix":"","StreetPreType":"","StreetName":"BROADWAY","StreetType":"","StreetSuffix":"N","VenueName":"FGO","CallType":"Loud Party/People","NatureOfCall":"LOUD PARTY","DateString":"4/7/2012 7:28:35 AM","Block":500,"VenueDescription":"Fargo","IncidentNumber":"2012-00019938","Duration":"2924","Address":"500 BLK 1/2 BROADWAY N"},{"CFSID":-4799054,"AdditionalInfo":"","StreetPrefix":"","StreetPreType":"","StreetName":"PRAIRIEWOOD","StreetType":"CIR","StreetSuffix":"S","VenueName":"FGO","CallType":"Loud Party/People","NatureOfCall":"LOUD PARTY","DateString":"4/7/2012 7:25:30 AM","Block":300,"VenueDescription":"Fargo","IncidentNumber":"2012-00019937","Duration":"4391","Address":"300 BLK PRAIRIEWOOD CIR S"},{"CFSID":-4799053,"AdditionalInfo":"","StreetPrefix":"","StreetPreType":"","StreetName":"4","StreetType":"ST","StreetSuffix":"N","VenueName":"FGO","CallType":"Found Property","NatureOfCall":"FOUND WALLET","DateString":"4/7/2012 7:20:50 AM","Block":200,"VenueDescription":"Fargo","IncidentNumber":"2012-00019936","Duration":"1396","Address":"200 BLK 4 ST N"},{"CFSID":-4799047,"AdditionalInfo":"","StreetPrefix":"","StreetPreType":"","StreetName":"4","StreetType":"ST","StreetSuffix":"S","VenueName":"FGO","CallType":"Impaired Person","NatureOfCall":"1056 M/NB ON 4 ST","DateString":"4/7/2012 6:52:23 AM","Block":500,"VenueDescription":"Fargo","IncidentNumber":"2012-00019934","Duration":"976","Address":"500 BLK 4 ST S"},{"CFSID":-4799042,"AdditionalInfo":"","StreetPrefix":"","StreetPreType":"","StreetName":"9","StreetType":"ST","StreetSuffix":"S","VenueName":"FGO","CallType":"SU","NatureOfCall":"SUSP NOISE","DateString":"4/7/2012 6:17:28 AM","Block":100,"VenueDescription":"Fargo","IncidentNumber":"2012-00019931","Duration":"1185","Address":"100 BLK 9 ST S"},{"CFSID":-4799041,"AdditionalInfo":"","StreetPrefix":"","StreetPreType":"","StreetName":"UNIVERSITY","StreetType":"DR","StreetSuffix":"S","VenueName":"FGO","CallType":"Recovered NCIC","NatureOfCall":"RECOVERED STOLEN VEH","DateString":"4/7/2012 6:15:08 AM","Block":3000,"VenueDescription":"Fargo","IncidentNumber":"2012-00019930","Duration":"34143","Address":"3000 BLK UNIVERSITY DR S"},{"CFSID":-4799040,"AdditionalInfo":"","StreetPrefix":"","StreetPreType":"","StreetName":"ROBERTS","StreetType":"ST","StreetSuffix":"N","VenueName":"FGO","CallType":"Medical-C ","NatureOfCall":"MEDICAL","DateString":"4/7/2012 5:42:53 AM","Block":100,"VenueDescription":"Fargo","IncidentNumber":"Multiple incidents","Duration":"1377","Address":"100 BLK ROBERTS ST N"},{"CFSID":-4799038,"AdditionalInfo":"","StreetPrefix":"","StreetPreType":"","StreetName":"5","StreetType":"ST","StreetSuffix":"N","VenueName":"FGO","CallType":"Impaired Person","NatureOfCall":"1056 NA/M","DateString":"4/7/2012 5:36:36 AM","Block":300,"VenueDescription":"Fargo","IncidentNumber":"2012-00019929","Duration":"1769","Address":"300 BLK 5 ST N"},{"CFSID":-4799036,"AdditionalInfo":"","StreetPrefix":"","StreetPreType":"","StreetName":"18","StreetType":"ST","StreetSuffix":"N","VenueName":"FGO","CallType":"COP","NatureOfCall":"OUT WITH A BICYCLIST","DateString":"4/7/2012 5:20:31 AM","Block":1200,"VenueDescription":"Fargo","IncidentNumber":"2012-00003015","Duration":"2322","Address":"1200 BLK 18 ST N"},{"CFSID":-4799033,"AdditionalInfo":"","StreetPrefix":"","StreetPreType":"","StreetName":"34","StreetType":"ST","StreetSuffix":"S","VenueName":"FGO","CallType":"Medical-C ","NatureOfCall":"MEDICAL","DateString":"4/7/2012 4:53:03 AM","Block":1600,"VenueDescription":"Fargo","IncidentNumber":"Multiple incidents","Duration":"847","Address":"1600 BLK 34 ST S"},{"CFSID":-4799031,"AdditionalInfo":"","StreetPrefix":"E","StreetPreType":"","StreetName":"GATEWAY","StreetType":"CIR","StreetSuffix":"S","VenueName":"FGO","CallType":"Commercial Fire","NatureOfCall":"DECK FIRE\r\n","DateString":"4/7/2012 4:42:36 AM","Block":1500,"VenueDescription":"Fargo","IncidentNumber":"Multiple incidents","Duration":"1546","Address":"1500 BLK E GATEWAY CIR S"},{"CFSID":-4799030,"AdditionalInfo":"","StreetPrefix":"","StreetPreType":"","StreetName":"45","StreetType":"ST","StreetSuffix":"S","VenueName":"FGO","CallType":"Loud Party/People","NatureOfCall":"LOUD PARTY","DateString":"4/7/2012 4:33:46 AM","Block":1000,"VenueDescription":"Fargo","IncidentNumber":"Multiple incidents","Duration":"4451","Address":"1000 BLK 45 ST S"},{"CFSID":-4799025,"AdditionalInfo":"","StreetPrefix":"","StreetPreType":"","StreetName":"1","StreetType":"AVE","StreetSuffix":"N","VenueName":"FGO","CallType":"SU","NatureOfCall":"SUSP M ON BRIDGE","DateString":"4/7/2012 4:02:01 AM","Block":0,"VenueDescription":"Fargo","IncidentNumber":"2012-00019924","Duration":"989","Address":" 1 AVE N"},{"CFSID":-4799024,"AdditionalInfo":"","StreetPrefix":"","StreetPreType":"","StreetName":"5","StreetType":"ST","StreetSuffix":"S","VenueName":"FGO","CallType":"Domestic","NatureOfCall":"VERBAL ARGUMENT","DateString":"4/7/2012 3:55:07 AM","Block":900,"VenueDescription":"Fargo","IncidentNumber":"2012-00019922","Duration":"4780","Address":"900 BLK 5 ST S"},{"CFSID":-4799018,"AdditionalInfo":"","StreetPrefix":"","StreetPreType":"","StreetName":"13","StreetType":"AVE","StreetSuffix":"S","VenueName":"FGO","CallType":"Suicidal Person","NatureOfCall":"SUICIDAL F\r\n","DateString":"4/7/2012 3:45:35 AM","Block":0,"VenueDescription":"Fargo","IncidentNumber":"2012-00019919","Duration":"2237","Address":" 13 AVE S"},{"CFSID":-4799017,"AdditionalInfo":"","StreetPrefix":"","StreetPreType":"","StreetName":"BISHOPS","StreetType":"BLVD","StreetSuffix":"S","VenueName":"FGO","CallType":"Disturbance","NatureOfCall":"M TRYING TO GET INTO THE HOUSE","DateString":"4/7/2012 3:44:54 AM","Block":5400,"VenueDescription":"Fargo","IncidentNumber":"2012-00019920","Duration":"1096","Address":"5400 BLK BISHOPS BLVD S"},{"CFSID":-4799016,"AdditionalInfo":"","StreetPrefix":"","StreetPreType":"","StreetName":"13","StreetType":"AVE","StreetSuffix":"S","VenueName":"FGO","CallType":"Impaired Driver","NatureOfCall":"1055","DateString":"4/7/2012 3:40:50 AM","Block":0,"VenueDescription":"Fargo","IncidentNumber":"2012-00019918","Duration":"327","Address":" 13 AVE S"},{"CFSID":-4799012,"AdditionalInfo":"","StreetPrefix":"","StreetPreType":"","StreetName":"3","StreetType":"ST","StreetSuffix":"N","VenueName":"FGO","CallType":"Suicidal Person","NatureOfCall":"SUICIDAL F","DateString":"4/7/2012 3:03:58 AM","Block":800,"VenueDescription":"Fargo","IncidentNumber":"Multiple incidents","Duration":"3023","Address":"800 BLK 3 ST N"},{"CFSID":-4799011,"AdditionalInfo":"","StreetPrefix":"","StreetPreType":"","StreetName":"15","StreetType":"AVE","StreetSuffix":"S","VenueName":"FGO","CallType":"Commercial Fire","NatureOfCall":"CMF","DateString":"4/7/2012 2:57:30 AM","Block":3300,"VenueDescription":"Fargo","IncidentNumber":"Multiple incidents","Duration":"2652","Address":"3300 BLK 15 AVE S"},{"CFSID":-4799009,"AdditionalInfo":"","StreetPrefix":"","StreetPreType":"","StreetName":"11","StreetType":"AVE","StreetSuffix":"N","VenueName":"FGO","CallType":"BKOA","NatureOfCall":"BACKING UP FARGO PD","DateString":"4/7/2012 2:56:18 AM","Block":1700,"VenueDescription":"Fargo","IncidentNumber":"2012-00003014","Duration":"230","Address":"1700 BLK 11 AVE N"},{"CFSID":-4799008,"AdditionalInfo":"","StreetPrefix":"","StreetPreType":"","StreetName":"13","StreetType":"AVE","StreetSuffix":"S","VenueName":"FGO","CallType":"Alarm","NatureOfCall":"1090/SEARS","DateString":"4/7/2012 2:56:06 AM","Block":3900,"VenueDescription":"Fargo","IncidentNumber":"2012-00019915","Duration":"582","Address":"3900 BLK 13 AVE S"},{"CFSID":-4799006,"AdditionalInfo":"","StreetPrefix":"","StreetPreType":"","StreetName":"5","StreetType":"ST","StreetSuffix":"S","VenueName":"FGO","CallType":"Domestic","NatureOfCall":"VERBAL DOMESTIC","DateString":"4/7/2012 2:52:05 AM","Block":900,"VenueDescription":"Fargo","IncidentNumber":"2012-00019914","Duration":"2407","Address":"900 BLK 5 ST S"},{"CFSID":-4799004,"AdditionalInfo":"","StreetPrefix":"","StreetPreType":"","StreetName":"CALICO","StreetType":"DR","StreetSuffix":"S","VenueName":"FGO","CallType":"Impaired Driver","NatureOfCall":"1055","DateString":"4/7/2012 2:46:18 AM","Block":4300,"VenueDescription":"Fargo","IncidentNumber":"2012-00019911","Duration":"4127","Address":"4300 BLK CALICO DR S"},{"CFSID":-4798999,"AdditionalInfo":"","StreetPrefix":"","StreetPreType":"","StreetName":"UNIVERSITY","StreetType":"DR","StreetSuffix":"N","VenueName":"FGO","CallType":"Impaired Driver","NatureOfCall":"1055","DateString":"4/7/2012 2:35:00 AM","Block":1200,"VenueDescription":"Fargo","IncidentNumber":"2012-00019909","Duration":"411","Address":"1200 BLK UNIVERSITY DR N"},{"CFSID":-4798994,"AdditionalInfo":"","StreetPrefix":"","StreetPreType":"","StreetName":"UNIVERSITY","StreetType":"DR","StreetSuffix":"S","VenueName":"FGO","CallType":"Impaired Person","NatureOfCall":"1056 M","DateString":"4/7/2012 2:21:38 AM","Block":0,"VenueDescription":"Fargo","IncidentNumber":"2012-00019905","Duration":"228","Address":" UNIVERSITY DR S"},{"CFSID":-4798987,"AdditionalInfo":"","StreetPrefix":"","StreetPreType":"","StreetName":"4","StreetType":"ST","StreetSuffix":"N","VenueName":"FGO","CallType":"Impaired Person","NatureOfCall":"TRANSPORT 1056 M TO DTX","DateString":"4/7/2012 2:12:08 AM","Block":700,"VenueDescription":"Fargo","IncidentNumber":"2012-00019903","Duration":"1725","Address":"700 BLK 4 ST N"},{"CFSID":-4798986,"AdditionalInfo":"","StreetPrefix":"","StreetPreType":"","StreetName":"9","StreetType":"AVE","StreetSuffix":"S","VenueName":"FGO","CallType":"Recovered NCIC","NatureOfCall":"FOUND STOLEN VEH","DateString":"4/7/2012 2:10:00 AM","Block":1300,"VenueDescription":"Fargo","IncidentNumber":"","Duration":"981","Address":"1300 BLK 9 AVE S"},{"CFSID":-4798983,"AdditionalInfo":"","StreetPrefix":"","StreetPreType":"","StreetName":"25","StreetType":"ST","StreetSuffix":"S","VenueName":"FGO","CallType":"Impaired Driver","NatureOfCall":"1055","DateString":"4/7/2012 2:04:06 AM","Block":300,"VenueDescription":"Fargo","IncidentNumber":"2012-00019899","Duration":"2941","Address":"300 BLK 25 ST S"},{"CFSID":-4798973,"AdditionalInfo":"","StreetPrefix":"","StreetPreType":"","StreetName":"NORTHERN PACIFIC","StreetType":"AVE","StreetSuffix":"N","VenueName":"FGO","CallType":"Alarm","NatureOfCall":"AUDIBLE ALARM","DateString":"4/7/2012 1:53:35 AM","Block":500,"VenueDescription":"Fargo","IncidentNumber":"2012-00019896","Duration":"340","Address":"500 BLK NORTHERN PACIFIC AVE N"},{"CFSID":-4798972,"AdditionalInfo":"","StreetPrefix":"","StreetPreType":"","StreetName":"3","StreetType":"AVE","StreetSuffix":"N","VenueName":"FGO","CallType":"Impaired Person","NatureOfCall":"1056 F PASSED OUT","DateString":"4/7/2012 1:53:20 AM","Block":500,"VenueDescription":"Fargo","IncidentNumber":"Multiple incidents","Duration":"1458","Address":"500 BLK 3 AVE N"},{"CFSID":-4798969,"AdditionalInfo":"","StreetPrefix":"","StreetPreType":"","StreetName":"25","StreetType":"ST","StreetSuffix":"S","VenueName":"FGO","CallType":"Reckless Driving","NatureOfCall":"RECKLESS DRIVER","DateString":"4/7/2012 1:47:55 AM","Block":0,"VenueDescription":"Fargo","IncidentNumber":"2012-00019893","Duration":"321","Address":" 25 ST S"},{"CFSID":-4798968,"AdditionalInfo":"","StreetPrefix":"","StreetPreType":"","StreetName":"8","StreetType":"ST","StreetSuffix":"N","VenueName":"FGO","CallType":"SU","NatureOfCall":"O/W 2","DateString":"4/7/2012 1:43:10 AM","Block":0,"VenueDescription":"Fargo","IncidentNumber":"2012-00019892","Duration":"1161","Address":"0 BLK 8 ST N"},{"CFSID":-4798962,"AdditionalInfo":"","StreetPrefix":"","StreetPreType":"","StreetName":"10","StreetType":"ST","StreetSuffix":"N","VenueName":"FGO","CallType":"Disturbance","NatureOfCall":"FIGHT","DateString":"4/7/2012 1:24:04 AM","Block":300,"VenueDescription":"Fargo","IncidentNumber":"2012-00019889","Duration":"375","Address":"300 BLK 10 ST N"},{"CFSID":-4798958,"AdditionalInfo":"","StreetPrefix":"","StreetPreType":"","StreetName":"NORTHERN PACIFIC","StreetType":"AVE","StreetSuffix":"N","VenueName":"FGO","CallType":"Impaired Person","NatureOfCall":"O/W CONSUMER","DateString":"4/7/2012 1:13:55 AM","Block":600,"VenueDescription":"Fargo","IncidentNumber":"2012-00019888","Duration":"202","Address":"600 BLK NORTHERN PACIFIC AVE N"},{"CFSID":-4798955,"AdditionalInfo":"","StreetPrefix":"","StreetPreType":"","StreetName":"MAIN","StreetType":"AVE","StreetSuffix":"","VenueName":"FGO","CallType":"SU","NatureOfCall":"M RUNNING\r\n","DateString":"4/7/2012 1:05:50 AM","Block":1400,"VenueDescription":"Fargo","IncidentNumber":"","Duration":"101","Address":"1400 BLK MAIN AVE"},{"CFSID":-4798951,"AdditionalInfo":"","StreetPrefix":"","StreetPreType":"","StreetName":"6","StreetType":"AVE","StreetSuffix":"N","VenueName":"FGO","CallType":"Disturbance","NatureOfCall":"SOMEONE TRYING TO BREAK DOOR DOWN","DateString":"4/7/2012 1:00:56 AM","Block":900,"VenueDescription":"Fargo","IncidentNumber":"2012-00019886","Duration":"1052","Address":"900 BLK 6 AVE N"},{"CFSID":-4798946,"AdditionalInfo":"","StreetPrefix":"","StreetPreType":"","StreetName":"1","StreetType":"AVE","StreetSuffix":"S","VenueName":"FGO","CallType":"Impaired Person","NatureOfCall":"1056 M LEFT DTX","DateString":"4/7/2012 12:51:39 AM","Block":1500,"VenueDescription":"Fargo","IncidentNumber":"Multiple incidents","Duration":"2950","Address":"1500 BLK 1 AVE S"},{"CFSID":-4798945,"AdditionalInfo":"","StreetPrefix":"","StreetPreType":"","StreetName":"NORTHERN PACIFIC","StreetType":"AVE","StreetSuffix":"N","VenueName":"FGO","CallType":"Alarm","NatureOfCall":"1090 ","DateString":"4/7/2012 12:49:31 AM","Block":400,"VenueDescription":"Fargo","IncidentNumber":"2012-00019882","Duration":"536","Address":"400 BLK NORTHERN PACIFIC AVE N"},{"CFSID":-4798944,"AdditionalInfo":"","StreetPrefix":"","StreetPreType":"","StreetName":"3","StreetType":"AVE","StreetSuffix":"S","VenueName":"FGO","CallType":"Impound","NatureOfCall":"DEL TICKETS","DateString":"4/7/2012 12:48:36 AM","Block":2400,"VenueDescription":"Fargo","IncidentNumber":"2012-00019881","Duration":"4990","Address":"2400 BLK 3 AVE S"},{"CFSID":-4798942,"AdditionalInfo":"","StreetPrefix":"","StreetPreType":"","StreetName":"4","StreetType":"ST","StreetSuffix":"N","VenueName":"FGO","CallType":"Impaired Person","NatureOfCall":"ESCORT 1056 M TO DETOX","DateString":"4/7/2012 12:45:33 AM","Block":700,"VenueDescription":"Fargo","IncidentNumber":"2012-00019885","Duration":"1299","Address":"700 BLK 4 ST N"},{"CFSID":-4798939,"AdditionalInfo":"","StreetPrefix":"","StreetPreType":"","StreetName":"40","StreetType":"ST","StreetSuffix":"S","VenueName":"FGO","CallType":"Suicidal Person","NatureOfCall":"SUICIDAL F","DateString":"4/7/2012 12:44:24 AM","Block":1800,"VenueDescription":"Fargo","IncidentNumber":"Multiple incidents","Duration":"2362","Address":"1800 BLK 40 ST S"},{"CFSID":-4798933,"AdditionalInfo":"","StreetPrefix":"","StreetPreType":"","StreetName":"MAIN","StreetType":"AVE","StreetSuffix":"","VenueName":"FGO","CallType":"Impaired Driver","NatureOfCall":"1055","DateString":"4/7/2012 12:34:54 AM","Block":2700,"VenueDescription":"Fargo","IncidentNumber":"2012-00019875","Duration":"295","Address":"2700 BLK MAIN AVE"},{"CFSID":-4798931,"AdditionalInfo":"","StreetPrefix":"","StreetPreType":"","StreetName":"16","StreetType":"AVE","StreetSuffix":"S","VenueName":"FGO","CallType":"SU","NatureOfCall":"SUSP PEOPLE","DateString":"4/7/2012 12:31:25 AM","Block":4800,"VenueDescription":"Fargo","IncidentNumber":"2012-00019874","Duration":"385","Address":"4800 BLK 16 AVE S"},{"CFSID":-4798928,"AdditionalInfo":"","StreetPrefix":"","StreetPreType":"","StreetName":"1","StreetType":"AVE","StreetSuffix":"N","VenueName":"FGO","CallType":"Parking Complaint","NatureOfCall":"BLK DODGE CHARGER BLOCKING FIRE HYDRANT","DateString":"4/7/2012 12:26:12 AM","Block":600,"VenueDescription":"Fargo","IncidentNumber":"2012-00019873","Duration":"160","Address":"600 BLK 1 AVE N"},{"CFSID":-4798922,"AdditionalInfo":"","StreetPrefix":"","StreetPreType":"","StreetName":"16","StreetType":"AVE","StreetSuffix":"S","VenueName":"FGO","CallType":"Disturbance","NatureOfCall":"M KEEPS RINGING BUZZER","DateString":"4/7/2012 12:15:26 AM","Block":4800,"VenueDescription":"Fargo","IncidentNumber":"","Duration":"260","Address":"4800 BLK 16 AVE S"},{"CFSID":-4798921,"AdditionalInfo":"","StreetPrefix":"","StreetPreType":"","StreetName":"UNIVERSITY","StreetType":"DR","StreetSuffix":"N","VenueName":"FGO","CallType":"BKOA","NatureOfCall":"BACKING UP FARGO PD","DateString":"4/7/2012 12:14:39 AM","Block":1300,"VenueDescription":"Fargo","IncidentNumber":"2012-00003010","Duration":"223","Address":"1300 BLK UNIVERSITY DR N"},{"CFSID":-4798919,"AdditionalInfo":"","StreetPrefix":"","StreetPreType":"","StreetName":"17","StreetType":"ST","StreetSuffix":"S","VenueName":"FGO","CallType":"Commercial Fire","NatureOfCall":"CMF","DateString":"4/7/2012 12:14:04 AM","Block":3300,"VenueDescription":"Fargo","IncidentNumber":"Multiple incidents","Duration":"1852","Address":"3300 BLK 17 ST S"},{"CFSID":-4798918,"AdditionalInfo":"","StreetPrefix":"","StreetPreType":"","StreetName":"PACIFIC","StreetType":"DR","StreetSuffix":"S","VenueName":"FGO","CallType":"Assault","NatureOfCall":"ASSAULT","DateString":"4/7/2012 12:13:59 AM","Block":2600,"VenueDescription":"Fargo","IncidentNumber":"2012-00019869","Duration":"3440","Address":"2600 BLK PACIFIC DR S"},{"CFSID":-4798915,"AdditionalInfo":"","StreetPrefix":"","StreetPreType":"","StreetName":"NORTHERN PACIFIC","StreetType":"AVE","StreetSuffix":"N","VenueName":"FGO","CallType":"Impaired Person","NatureOfCall":"1056 M","DateString":"4/7/2012 12:10:38 AM","Block":1000,"VenueDescription":"Fargo","IncidentNumber":"Multiple incidents","Duration":"940","Address":"1000 BLK NORTHERN PACIFIC AVE N"},{"CFSID":-4798912,"AdditionalInfo":"","StreetPrefix":"","StreetPreType":"","StreetName":"PRAIRIEWOOD","StreetType":"DR","StreetSuffix":"S","VenueName":"FGO","CallType":"Impaired Driver","NatureOfCall":"1055","DateString":"4/7/2012 12:08:26 AM","Block":200,"VenueDescription":"Fargo","IncidentNumber":"2012-00019864","Duration":"3119","Address":"200 BLK PRAIRIEWOOD DR S"}]}