{"DispatchLog":[{"CFSID":-4702322,"AdditionalInfo":"","StreetPrefix":"","StreetPreType":"","StreetName":"BROADWAY","StreetType":"","StreetSuffix":"N","VenueName":"FGO","CallType":"Alarm","NatureOfCall":"1090","DateString":"10/13/2011 11:56:54 PM","Block":0,"VenueDescription":"Fargo","IncidentNumber":"2011-00078384","Duration":"464","Address":"0 BLK BROADWAY N"},{"CFSID":-4702321,"AdditionalInfo":"","StreetPrefix":"","StreetPreType":"","StreetName":"VETERANS","StreetType":"BLVD","StreetSuffix":"","VenueName":"FGO","CallType":"TC","NatureOfCall":"DUS","DateString":"10/13/2011 11:51:59 PM","Block":3900,"VenueDescription":"Fargo","IncidentNumber":"2011-00040995","Duration":"3092","Address":"3900 BLK VETERANS BLVD"},{"CFSID":-4702314,"AdditionalInfo":"","StreetPrefix":"","StreetPreType":"","StreetName":"15","StreetType":"AVE","StreetSuffix":"S","VenueName":"FGO","CallType":"Loud Party/People","NatureOfCall":"LOUD PARTY","DateString":"10/13/2011 11:46:30 PM","Block":4300,"VenueDescription":"Fargo","IncidentNumber":"2011-00078383","Duration":"1832","Address":"4300 BLK 15 AVE S"},{"CFSID":-4702297,"AdditionalInfo":"","StreetPrefix":"","StreetPreType":"","StreetName":"19","StreetType":"ST","StreetSuffix":"N","VenueName":"FGO","CallType":"Vandalism","NatureOfCall":"VANDALISM TO FENCE/15 MIN DELAY","DateString":"10/13/2011 10:59:55 PM","Block":1100,"VenueDescription":"Fargo","IncidentNumber":"2011-00078378","Duration":"1705","Address":"1100 BLK 19 ST N"},{"CFSID":-4702294,"AdditionalInfo":"","StreetPrefix":"","StreetPreType":"","StreetName":"5","StreetType":"ST","StreetSuffix":"S","VenueName":"FGO","CallType":"SU","NatureOfCall":"SUSP PEOPLE","DateString":"10/13/2011 10:52:27 PM","Block":2400,"VenueDescription":"Fargo","IncidentNumber":"2011-00078377","Duration":"1210","Address":"2400 BLK 5 ST S"},{"CFSID":-4702292,"AdditionalInfo":"","StreetPrefix":"","StreetPreType":"","StreetName":"25","StreetType":"ST","StreetSuffix":"S","VenueName":"FGO","CallType":"Robbery","NatureOfCall":"ROBBERY JUST HAPPENED","DateString":"10/13/2011 10:49:00 PM","Block":3000,"VenueDescription":"Fargo","IncidentNumber":"2011-00078376","Duration":"5306","Address":"3000 BLK 25 ST S"},{"CFSID":-4702281,"AdditionalInfo":"","StreetPrefix":"","StreetPreType":"","StreetName":"ADMINISTRATION","StreetType":"AVE","StreetSuffix":"N","VenueName":"FGO","CallType":"Escort NDSU","NatureOfCall":"ESCORT","DateString":"10/13/2011 10:26:55 PM","Block":1400,"VenueDescription":"Fargo","IncidentNumber":"2011-00037725","Duration":"760","Address":"1400 BLK ADMINISTRATION AVE N"},{"CFSID":-4702279,"AdditionalInfo":"","StreetPrefix":"","StreetPreType":"","StreetName":"6","StreetType":"AVE","StreetSuffix":"S","VenueName":"FGO","CallType":"Loud Noise","NatureOfCall":"PEOPLE ARE RUNNING UP AND DOWN THE STAIRS","DateString":"10/13/2011 10:24:00 PM","Block":2200,"VenueDescription":"Fargo","IncidentNumber":"","Duration":"261","Address":"2200 BLK 6 AVE S"},{"CFSID":-4702272,"AdditionalInfo":"","StreetPrefix":"","StreetPreType":"","StreetName":"ADMINISTRATION","StreetType":"AVE","StreetSuffix":"N","VenueName":"FGO","CallType":"Escort NDSU","NatureOfCall":"ESCORT","DateString":"10/13/2011 10:12:39 PM","Block":1400,"VenueDescription":"Fargo","IncidentNumber":"2011-00037722","Duration":"792","Address":"1400 BLK ADMINISTRATION AVE N"},{"CFSID":-4702270,"AdditionalInfo":"","StreetPrefix":"","StreetPreType":"","StreetName":"9 1/2","StreetType":"ST","StreetSuffix":"N","VenueName":"FGO","CallType":"Welfare Check","NatureOfCall":"WELFARE CHECK ON F","DateString":"10/13/2011 10:07:07 PM","Block":2100,"VenueDescription":"Fargo","IncidentNumber":"2011-00078369","Duration":"2425","Address":"2100 BLK 9 1/2 ST N"},{"CFSID":-4702267,"AdditionalInfo":"","StreetPrefix":"","StreetPreType":"","StreetName":"DOWNTOWN","StreetType":"","StreetSuffix":"","VenueName":"FGO","CallType":"COP","NatureOfCall":"COP","DateString":"10/13/2011 10:05:47 PM","Block":0,"VenueDescription":"Fargo","IncidentNumber":"2011-00078368","Duration":"1133","Address":" DOWNTOWN"},{"CFSID":-4702266,"AdditionalInfo":"","StreetPrefix":"","StreetPreType":"","StreetName":"ALBRECHT","StreetType":"BLVD","StreetSuffix":"N","VenueName":"FGO","CallType":"Impaired Person","NatureOfCall":"POSS IMPAIRED PERSONS","DateString":"10/13/2011 10:04:27 PM","Block":1300,"VenueDescription":"Fargo","IncidentNumber":"2011-00037720","Duration":"490","Address":"1300 BLK ALBRECHT BLVD N"},{"CFSID":-4702265,"AdditionalInfo":"","StreetPrefix":"","StreetPreType":"","StreetName":"6","StreetType":"AVE","StreetSuffix":"S","VenueName":"FGO","CallType":"Recovered NCIC","NatureOfCall":"RECOVERED JUV RUNAWAY","DateString":"10/13/2011 10:03:04 PM","Block":2200,"VenueDescription":"Fargo","IncidentNumber":"2011-00078372","Duration":"4153","Address":"2200 BLK 6 AVE S"},{"CFSID":-4702258,"AdditionalInfo":"","StreetPrefix":"","StreetPreType":"","StreetName":"33","StreetType":"ST","StreetSuffix":"S","VenueName":"FGO","CallType":"Domestic","NatureOfCall":"DOMESTIC / SUICIDAL M","DateString":"10/13/2011 9:47:38 PM","Block":3100,"VenueDescription":"Fargo","IncidentNumber":"Multiple incidents","Duration":"2616","Address":"3100 BLK 33 ST S"},{"CFSID":-4702254,"AdditionalInfo":"","StreetPrefix":"","StreetPreType":"","StreetName":"BROADWAY","StreetType":"","StreetSuffix":"N","VenueName":"FGO","CallType":"Domestic","NatureOfCall":"DOMESTIC","DateString":"10/13/2011 9:38:47 PM","Block":0,"VenueDescription":"Fargo","IncidentNumber":"2011-00078363","Duration":"426","Address":"0 BLK BROADWAY N"},{"CFSID":-4702250,"AdditionalInfo":"","StreetPrefix":"","StreetPreType":"","StreetName":"35","StreetType":"ST","StreetSuffix":"S","VenueName":"FGO","CallType":"Theft","NatureOfCall":"THEFT DELAYED REPORT","DateString":"10/13/2011 9:24:44 PM","Block":1600,"VenueDescription":"Fargo","IncidentNumber":"","Duration":"153","Address":"1600 BLK 35 ST S"},{"CFSID":-4702249,"AdditionalInfo":"","StreetPrefix":"","StreetPreType":"","StreetName":"11","StreetType":"AVE","StreetSuffix":"N","VenueName":"FGO","CallType":"Impaired Person","NatureOfCall":"1056 M","DateString":"10/13/2011 9:16:09 PM","Block":0,"VenueDescription":"Fargo","IncidentNumber":"Multiple incidents","Duration":"1849","Address":" 11 AVE N"},{"CFSID":-4702248,"AdditionalInfo":"","StreetPrefix":"","StreetPreType":"","StreetName":"13","StreetType":"AVE","StreetSuffix":"S","VenueName":"FGO","CallType":"Shoplifting","NatureOfCall":"2 A/F SHOPLIFTERS","DateString":"10/13/2011 9:12:23 PM","Block":4700,"VenueDescription":"Fargo","IncidentNumber":"2011-00078362","Duration":"4477","Address":"4700 BLK 13 AVE S"},{"CFSID":-4702245,"AdditionalInfo":"","StreetPrefix":"E","StreetPreType":"","StreetName":"GATEWAY","StreetType":"CIR","StreetSuffix":"S","VenueName":"FGO","CallType":"SU","NatureOfCall":"SUSP VEHS","DateString":"10/13/2011 9:06:55 PM","Block":1400,"VenueDescription":"Fargo","IncidentNumber":"2011-00078360","Duration":"1552","Address":"1400 BLK E GATEWAY CIR S"},{"CFSID":-4702244,"AdditionalInfo":"","StreetPrefix":"","StreetPreType":"","StreetName":"19","StreetType":"AVE","StreetSuffix":"N","VenueName":"FGO","CallType":"Accident - Injury","NatureOfCall":"1050 I","DateString":"10/13/2011 9:05:14 PM","Block":1300,"VenueDescription":"Fargo","IncidentNumber":"Multiple incidents","Duration":"5054","Address":"1300 BLK 19 AVE N"},{"CFSID":-4702241,"AdditionalInfo":"","StreetPrefix":"","StreetPreType":"","StreetName":"ADMINISTRATION","StreetType":"AVE","StreetSuffix":"N","VenueName":"FGO","CallType":"Escort NDSU","NatureOfCall":"ESCORT","DateString":"10/13/2011 9:03:38 PM","Block":1300,"VenueDescription":"Fargo","IncidentNumber":"2011-00037719","Duration":"1405","Address":"1300 BLK ADMINISTRATION AVE N"},{"CFSID":-4702238,"AdditionalInfo":"","StreetPrefix":"","StreetPreType":"","StreetName":"7","StreetType":"AVE","StreetSuffix":"S","VenueName":"FGO","CallType":"Impaired Person","NatureOfCall":"1056 M","DateString":"10/13/2011 9:00:23 PM","Block":4500,"VenueDescription":"Fargo","IncidentNumber":"2011-00078357","Duration":"1559","Address":"4500 BLK 7 AVE S"},{"CFSID":-4702234,"AdditionalInfo":"","StreetPrefix":"","StreetPreType":"","StreetName":"35","StreetType":"AVE","StreetSuffix":"S","VenueName":"FGO","CallType":"Impaired Driver","NatureOfCall":"1050 P  1055 DRIVER","DateString":"10/13/2011 8:52:08 PM","Block":1600,"VenueDescription":"Fargo","IncidentNumber":"2011-00078355","Duration":"5966","Address":"1600 BLK 35 AVE S"},{"CFSID":-4702232,"AdditionalInfo":"","StreetPrefix":"","StreetPreType":"","StreetName":"10","StreetType":"ST","StreetSuffix":"N","VenueName":"FGO","CallType":"Commercial Fire","NatureOfCall":"CMF","DateString":"10/13/2011 8:51:41 PM","Block":1800,"VenueDescription":"Fargo","IncidentNumber":"2011-00032952","Duration":"936","Address":"1800 BLK 10 ST N"},{"CFSID":-4702231,"AdditionalInfo":"","StreetPrefix":"","StreetPreType":"","StreetName":"10","StreetType":"ST","StreetSuffix":"N","VenueName":"FGO","CallType":"Commercial Fire","NatureOfCall":"CMF","DateString":"10/13/2011 8:51:11 PM","Block":1800,"VenueDescription":"Fargo","IncidentNumber":"2011-00037717","Duration":"1055","Address":"1800 BLK 10 ST N"},{"CFSID":-4702227,"AdditionalInfo":"","StreetPrefix":"","StreetPreType":"","StreetName":"13","StreetType":"AVE","StreetSuffix":"S","VenueName":"FGO","CallType":"Welfare Check","NatureOfCall":"WELFARE CHECK ON M","DateString":"10/13/2011 8:37:44 PM","Block":2200,"VenueDescription":"Fargo","IncidentNumber":"2011-00078352","Duration":"801","Address":"2200 BLK 13 AVE S"},{"CFSID":-4702224,"AdditionalInfo":"","StreetPrefix":"","StreetPreType":"","StreetName":"42","StreetType":"AVE","StreetSuffix":"S","VenueName":"FGO","CallType":"Missing Person","NatureOfCall":"MISSING M","DateString":"10/13/2011 8:30:31 PM","Block":3500,"VenueDescription":"Fargo","IncidentNumber":"","Duration":"299","Address":"3500 BLK 42 AVE S"},{"CFSID":-4702223,"AdditionalInfo":"","StreetPrefix":"","StreetPreType":"","StreetName":"UNIVERSITY","StreetType":"DR","StreetSuffix":"S","VenueName":"FGO","CallType":"Commercial Fire","NatureOfCall":"COMMERCIAL FIRE ALARM","DateString":"10/13/2011 8:29:11 PM","Block":1700,"VenueDescription":"Fargo","IncidentNumber":"2011-00032951","Duration":"1108","Address":"1700 BLK UNIVERSITY DR S"},{"CFSID":-4702217,"AdditionalInfo":"","StreetPrefix":"","StreetPreType":"","StreetName":"17","StreetType":"AVE","StreetSuffix":"S","VenueName":"FGO","CallType":"Accident - Property","NatureOfCall":"1050 H & R /15 MIN DELAY","DateString":"10/13/2011 8:20:20 PM","Block":4300,"VenueDescription":"Fargo","IncidentNumber":"2011-00078349","Duration":"2373","Address":"4300 BLK 17 AVE S"},{"CFSID":-4702216,"AdditionalInfo":"","StreetPrefix":"","StreetPreType":"","StreetName":"ADMINISTRATION","StreetType":"AVE","StreetSuffix":"N","VenueName":"FGO","CallType":"Escort NDSU","NatureOfCall":"ESCORT","DateString":"10/13/2011 8:19:08 PM","Block":1400,"VenueDescription":"Fargo","IncidentNumber":"2011-00037715","Duration":"1066","Address":"1400 BLK ADMINISTRATION AVE N"},{"CFSID":-4702215,"AdditionalInfo":"","StreetPrefix":"","StreetPreType":"","StreetName":"25","StreetType":"ST","StreetSuffix":"S","VenueName":"FGO","CallType":"TC","NatureOfCall":"EXPIRED PLATES / BIG TOP BINGO","DateString":"10/13/2011 8:18:59 PM","Block":900,"VenueDescription":"Fargo","IncidentNumber":"2011-00078350","Duration":"380","Address":"900 BLK 25 ST S"},{"CFSID":-4702212,"AdditionalInfo":"","StreetPrefix":"","StreetPreType":"","StreetName":"11","StreetType":"AVE","StreetSuffix":"S","VenueName":"FGO","CallType":"Welfare Check","NatureOfCall":"WELFARE CHECK","DateString":"10/13/2011 8:07:06 PM","Block":2200,"VenueDescription":"Fargo","IncidentNumber":"2011-00078347","Duration":"2047","Address":"2200 BLK 11 AVE S"},{"CFSID":-4702208,"AdditionalInfo":"","StreetPrefix":"","StreetPreType":"","StreetName":"42","StreetType":"ST","StreetSuffix":"S","VenueName":"FGO","CallType":"SU","NatureOfCall":"SUSP TENT","DateString":"10/13/2011 8:03:55 PM","Block":3500,"VenueDescription":"Fargo","IncidentNumber":"2011-00078348","Duration":"1558","Address":"3500 BLK 42 ST S"},{"CFSID":-4702197,"AdditionalInfo":"","StreetPrefix":"","StreetPreType":"","StreetName":"ROGER MARIS","StreetType":"DR","StreetSuffix":"S","VenueName":"FGO","CallType":"Bicycle - Found","NatureOfCall":"FOUND BIKE","DateString":"10/13/2011 7:36:42 PM","Block":1900,"VenueDescription":"Fargo","IncidentNumber":"","Duration":"181","Address":"1900 BLK ROGER MARIS DR S"},{"CFSID":-4702193,"AdditionalInfo":"","StreetPrefix":"","StreetPreType":"","StreetName":"19","StreetType":"AVE","StreetSuffix":"N","VenueName":"FGO","CallType":"Impaired Driver","NatureOfCall":"1055 M","DateString":"10/13/2011 7:34:01 PM","Block":1500,"VenueDescription":"Fargo","IncidentNumber":"","Duration":"292","Address":"1500 BLK 19 AVE N"},{"CFSID":-4702192,"AdditionalInfo":"","StreetPrefix":"","StreetPreType":"","StreetName":"10","StreetType":"ST","StreetSuffix":"N","VenueName":"FGO","CallType":"Impaired Person","NatureOfCall":"1056 m requesting detox / stop n go","DateString":"10/13/2011 7:33:29 PM","Block":300,"VenueDescription":"Fargo","IncidentNumber":"2011-00078340","Duration":"1645","Address":"300 BLK 10 ST N"},{"CFSID":-4702190,"AdditionalInfo":"","StreetPrefix":"","StreetPreType":"","StreetName":"23","StreetType":"ST","StreetSuffix":"S","VenueName":"FGO","CallType":"Disturbance","NatureOfCall":"DISTURBANCE","DateString":"10/13/2011 7:23:08 PM","Block":700,"VenueDescription":"Fargo","IncidentNumber":"2011-00078339","Duration":"1231","Address":"700 BLK 23 ST S"},{"CFSID":-4702189,"AdditionalInfo":"","StreetPrefix":"","StreetPreType":"","StreetName":"WHITESTONE","StreetType":"CIR","StreetSuffix":"S","VenueName":"FGO","CallType":"Animal Calls","NatureOfCall":"BARKING DOGS","DateString":"10/13/2011 7:22:20 PM","Block":1700,"VenueDescription":"Fargo","IncidentNumber":"2011-00078342","Duration":"2128","Address":"1700 BLK WHITESTONE CIR S"},{"CFSID":-4702187,"AdditionalInfo":"","StreetPrefix":"","StreetPreType":"","StreetName":"48","StreetType":"AVE","StreetSuffix":"S","VenueName":"FGO","CallType":"Parking Complaint","NatureOfCall":"VEH PARKED ON NO PARKING SIDE OF THE ST","DateString":"10/13/2011 7:18:49 PM","Block":4700,"VenueDescription":"Fargo","IncidentNumber":"2011-00078338","Duration":"1253","Address":"4700 BLK 48 AVE S"},{"CFSID":-4702185,"AdditionalInfo":"","StreetPrefix":"","StreetPreType":"","StreetName":"7","StreetType":"AVE","StreetSuffix":"N","VenueName":"FGO","CallType":"Impaired Driver","NatureOfCall":"1055 DRIVER/ 15 MIN DELAY","DateString":"10/13/2011 7:14:35 PM","Block":0,"VenueDescription":"Fargo","IncidentNumber":"","Duration":"612","Address":" 7 AVE N"},{"CFSID":-4702183,"AdditionalInfo":"","StreetPrefix":"","StreetPreType":"","StreetName":"4","StreetType":"ST","StreetSuffix":"N","VenueName":"FGO","CallType":"Impaired Person","NatureOfCall":"10-56/F SANFORD FOR DETOX","DateString":"10/13/2011 7:14:20 PM","Block":700,"VenueDescription":"Fargo","IncidentNumber":"2011-00078337","Duration":"1569","Address":"700 BLK 4 ST N"},{"CFSID":-4702176,"AdditionalInfo":"","StreetPrefix":"","StreetPreType":"","StreetName":"44","StreetType":"ST","StreetSuffix":"S","VenueName":"FGO","CallType":"Stolen Vehicle","NatureOfCall":"INFO REGARDING STOLEN VEH","DateString":"10/13/2011 6:53:29 PM","Block":900,"VenueDescription":"Fargo","IncidentNumber":"2011-00078336","Duration":"2305","Address":"900 BLK 44 ST S"},{"CFSID":-4702172,"AdditionalInfo":"","StreetPrefix":"","StreetPreType":"","StreetName":"45","StreetType":"ST","StreetSuffix":"S","VenueName":"FGO","CallType":"Accident - Property","NatureOfCall":"1050 H & R DELAYED REPORT","DateString":"10/13/2011 6:50:51 PM","Block":2500,"VenueDescription":"Fargo","IncidentNumber":"2011-00078334","Duration":"1291","Address":"2500 BLK 45 ST S"},{"CFSID":-4702170,"AdditionalInfo":"","StreetPrefix":"","StreetPreType":"","StreetName":"NORTHERN PACIFIC","StreetType":"AVE","StreetSuffix":"N","VenueName":"FGO","CallType":"Impaired Person","NatureOfCall":"1056F","DateString":"10/13/2011 6:46:00 PM","Block":700,"VenueDescription":"Fargo","IncidentNumber":"","Duration":"85","Address":"700 BLK NORTHERN PACIFIC AVE N"},{"CFSID":-4702168,"AdditionalInfo":"","StreetPrefix":"","StreetPreType":"","StreetName":"NORTHERN PACIFIC","StreetType":"AVE","StreetSuffix":"N","VenueName":"FGO","CallType":"Impaired Person","NatureOfCall":"1056 F","DateString":"10/13/2011 6:42:00 PM","Block":700,"VenueDescription":"Fargo","IncidentNumber":"2011-00078335","Duration":"2277","Address":"700 BLK NORTHERN PACIFIC AVE N"},{"CFSID":-4702162,"AdditionalInfo":"","StreetPrefix":"","StreetPreType":"","StreetName":"27","StreetType":"ST","StreetSuffix":"S","VenueName":"FGO","CallType":"Juvenile Complaint","NatureOfCall":"REMOVE UNRULY JUV ","DateString":"10/13/2011 6:27:49 PM","Block":3100,"VenueDescription":"Fargo","IncidentNumber":"Multiple incidents","Duration":"2208","Address":"3100 BLK 27 ST S"},{"CFSID":-4702160,"AdditionalInfo":"","StreetPrefix":"","StreetPreType":"","StreetName":"4","StreetType":"ST","StreetSuffix":"N","VenueName":"FGO","CallType":"Transport","NatureOfCall":"TRANSPORT FROM GRAND FORKS","DateString":"10/13/2011 6:26:31 PM","Block":200,"VenueDescription":"Fargo","IncidentNumber":"2011-00078330","Duration":"56","Address":"200 BLK 4 ST N"},{"CFSID":-4702157,"AdditionalInfo":"","StreetPrefix":"","StreetPreType":"","StreetName":"6","StreetType":"AVE","StreetSuffix":"S","VenueName":"FGO","CallType":"Missing Person","NatureOfCall":"RUNAWAY JUV F","DateString":"10/13/2011 6:20:13 PM","Block":2200,"VenueDescription":"Fargo","IncidentNumber":"2011-00078333","Duration":"5249","Address":"2200 BLK 6 AVE S"},{"CFSID":-4702149,"AdditionalInfo":"","StreetPrefix":"","StreetPreType":"","StreetName":"49","StreetType":"ST","StreetSuffix":"S","VenueName":"FGO","CallType":"Harassment","NatureOfCall":"NEIGHBOR DISPUTE 1021 ","DateString":"10/13/2011 6:00:50 PM","Block":1800,"VenueDescription":"Fargo","IncidentNumber":"2011-00078328","Duration":"842","Address":"1800 BLK 49 ST S"},{"CFSID":-4702141,"AdditionalInfo":"","StreetPrefix":"","StreetPreType":"","StreetName":"COUNTRYSIDE TRAILER","StreetType":"CT","StreetSuffix":"S","VenueName":"FGO","CallType":"Animal Calls","NatureOfCall":"MEAN CHIHUAHUA 1021","DateString":"10/13/2011 5:37:09 PM","Block":800,"VenueDescription":"Fargo","IncidentNumber":"2011-00078327","Duration":"3953","Address":"800 BLK COUNTRYSIDE TRAILER CT S"},{"CFSID":-4702136,"AdditionalInfo":"","StreetPrefix":"","StreetPreType":"","StreetName":"11","StreetType":"AVE","StreetSuffix":"N","VenueName":"FGO","CallType":"Impaired Person","NatureOfCall":"1056 M","DateString":"10/13/2011 5:29:05 PM","Block":300,"VenueDescription":"Fargo","IncidentNumber":"2011-00078323","Duration":"2540","Address":"300 BLK 11 AVE N"},{"CFSID":-4702134,"AdditionalInfo":"","StreetPrefix":"","StreetPreType":"","StreetName":"4","StreetType":"AVE","StreetSuffix":"N","VenueName":"FGO","CallType":"Elevator Emergency","NatureOfCall":"M STUCK IN ELEVATOR ON 2ND FLOOR AT HEALTH CARE CENTER","DateString":"10/13/2011 5:27:58 PM","Block":400,"VenueDescription":"Fargo","IncidentNumber":"2011-00032950","Duration":"1723","Address":"400 BLK 4 AVE N"},{"CFSID":-4702133,"AdditionalInfo":"","StreetPrefix":"","StreetPreType":"","StreetName":"25","StreetType":"ST","StreetSuffix":"S","VenueName":"FGO","CallType":"Accident - Property","NatureOfCall":"1050P","DateString":"10/13/2011 5:24:28 PM","Block":0,"VenueDescription":"Fargo","IncidentNumber":"2011-00078322","Duration":"1615","Address":" 25 ST S"},{"CFSID":-4702132,"AdditionalInfo":"","StreetPrefix":"","StreetPreType":"I","StreetName":"29","StreetType":"","StreetSuffix":"","VenueName":"FGO","CallType":"TC","NatureOfCall":"CAR STALLED IN MIDDLE OF RD","DateString":"10/13/2011 5:22:16 PM","Block":0,"VenueDescription":"Fargo","IncidentNumber":"2011-00078324","Duration":"1636","Address":" I 29"},{"CFSID":-4702129,"AdditionalInfo":"","StreetPrefix":"","StreetPreType":"","StreetName":"4","StreetType":"AVE","StreetSuffix":"S","VenueName":"FGO","CallType":"Accident - Property","NatureOfCall":"1050 H&R REPORT","DateString":"10/13/2011 5:11:58 PM","Block":800,"VenueDescription":"Fargo","IncidentNumber":"2011-00078325","Duration":"3118","Address":"800 BLK 4 AVE S"},{"CFSID":-4702128,"AdditionalInfo":"","StreetPrefix":"","StreetPreType":"","StreetName":"BROADWAY","StreetType":"","StreetSuffix":"N","VenueName":"FGO","CallType":"Accident - Property","NatureOfCall":"1050 P","DateString":"10/13/2011 5:11:51 PM","Block":0,"VenueDescription":"Fargo","IncidentNumber":"2011-00078326","Duration":"3032","Address":" BROADWAY N"},{"CFSID":-4702125,"AdditionalInfo":"","StreetPrefix":"","StreetPreType":"","StreetName":"31","StreetType":"AVE","StreetSuffix":"N","VenueName":"FGO","CallType":"Suicidal Person","NatureOfCall":"SUICIDAL M","DateString":"10/13/2011 5:04:40 PM","Block":500,"VenueDescription":"Fargo","IncidentNumber":"Multiple incidents","Duration":"3067","Address":"500 BLK 31 AVE N"},{"CFSID":-4702124,"AdditionalInfo":"","StreetPrefix":"","StreetPreType":"","StreetName":"14 1/2","StreetType":"ST","StreetSuffix":"S","VenueName":"FGO","CallType":"Violation of Court Order","NatureOfCall":"VIOLATION OF NO CONTACT ORDER","DateString":"10/13/2011 5:04:14 PM","Block":1500,"VenueDescription":"Fargo","IncidentNumber":"2011-00078319","Duration":"2158","Address":"1500 BLK 14 1/2 ST S"},{"CFSID":-4702121,"AdditionalInfo":"","StreetPrefix":"","StreetPreType":"","StreetName":"13","StreetType":"AVE","StreetSuffix":"S","VenueName":"FGO","CallType":"Accident - Property","NatureOfCall":"1050 P","DateString":"10/13/2011 4:57:00 PM","Block":3900,"VenueDescription":"Fargo","IncidentNumber":"2011-00078317","Duration":"3229","Address":"3900 BLK 13 AVE S"},{"CFSID":-4702118,"AdditionalInfo":"","StreetPrefix":"","StreetPreType":"","StreetName":"45","StreetType":"ST","StreetSuffix":"S","VenueName":"FGO","CallType":"Accident - Property","NatureOfCall":"1050 P - BLOCKING TRAFFIC","DateString":"10/13/2011 4:47:22 PM","Block":0,"VenueDescription":"Fargo","IncidentNumber":"2011-00078316","Duration":"3020","Address":" 45 ST S"},{"CFSID":-4702115,"AdditionalInfo":"","StreetPrefix":"","StreetPreType":"","StreetName":"13","StreetType":"AVE","StreetSuffix":"S","VenueName":"FGO","CallType":"Accident - Injury","NatureOfCall":"1050I VEH VS BIKE","DateString":"10/13/2011 4:41:22 PM","Block":0,"VenueDescription":"Fargo","IncidentNumber":"Multiple incidents","Duration":"2789","Address":" 13 AVE S"},{"CFSID":-4702109,"AdditionalInfo":"","StreetPrefix":"","StreetPreType":"","StreetName":"39","StreetType":"ST","StreetSuffix":"N","VenueName":"FGO","CallType":"Commercial Fire","NatureOfCall":"GEN FIRE","DateString":"10/13/2011 4:33:33 PM","Block":1300,"VenueDescription":"Fargo","IncidentNumber":"Multiple incidents","Duration":"830","Address":"1300 BLK 39 ST N"},{"CFSID":-4702105,"AdditionalInfo":"","StreetPrefix":"","StreetPreType":"","StreetName":"36","StreetType":"ST","StreetSuffix":"S","VenueName":"FGO","CallType":"Juvenile Complaint","NatureOfCall":"JUV ASSAULT/1021 ONLY","DateString":"10/13/2011 4:29:12 PM","Block":3700,"VenueDescription":"Fargo","IncidentNumber":"2011-00078311","Duration":"868","Address":"3700 BLK 36 ST S"},{"CFSID":-4702098,"AdditionalInfo":"","StreetPrefix":"","StreetPreType":"","StreetName":"12","StreetType":"AVE","StreetSuffix":"N","VenueName":"FGO","CallType":"Harassment","NatureOfCall":"HARASSMENT/THEFT","DateString":"10/13/2011 4:08:58 PM","Block":1500,"VenueDescription":"Fargo","IncidentNumber":"2011-00078310","Duration":"2921","Address":"1500 BLK 12 AVE N"},{"CFSID":-4702094,"AdditionalInfo":"","StreetPrefix":"","StreetPreType":"","StreetName":"20","StreetType":"ST","StreetSuffix":"N","VenueName":"FGO","CallType":"Residential Fire","NatureOfCall":"GARAGE FIRE","DateString":"10/13/2011 3:40:00 PM","Block":500,"VenueDescription":"Fargo","IncidentNumber":"Multiple incidents","Duration":"1515","Address":"500 BLK 20 ST N"},{"CFSID":-4702092,"AdditionalInfo":"","StreetPrefix":"","StreetPreType":"","StreetName":"11","StreetType":"ST","StreetSuffix":"N","VenueName":"FGO","CallType":"SU","NatureOfCall":"SUSP VEH","DateString":"10/13/2011 3:38:36 PM","Block":1500,"VenueDescription":"Fargo","IncidentNumber":"2011-00078309","Duration":"3318","Address":"1500 BLK 11 ST N"},{"CFSID":-4702089,"AdditionalInfo":"","StreetPrefix":"","StreetPreType":"","StreetName":"NORTHERN PACIFIC","StreetType":"AVE","StreetSuffix":"N","VenueName":"FGO","CallType":"SU","NatureOfCall":"OPEN DOOR","DateString":"10/13/2011 3:25:05 PM","Block":1000,"VenueDescription":"Fargo","IncidentNumber":"2011-00078305","Duration":"1030","Address":"1000 BLK NORTHERN PACIFIC AVE N"},{"CFSID":-4702087,"AdditionalInfo":"","StreetPrefix":"","StreetPreType":"","StreetName":"7","StreetType":"AVE","StreetSuffix":"S","VenueName":"FGO","CallType":"Accident - Property","NatureOfCall":"1050 H/R","DateString":"10/13/2011 3:21:50 PM","Block":2500,"VenueDescription":"Fargo","IncidentNumber":"2011-00078307","Duration":"2241","Address":"2500 BLK 7 AVE S"},{"CFSID":-4702073,"AdditionalInfo":"","StreetPrefix":"","StreetPreType":"","StreetName":"15","StreetType":"AVE","StreetSuffix":"N","VenueName":"FGO","CallType":"Impound","NatureOfCall":"IMPOUND","DateString":"10/13/2011 3:04:47 PM","Block":1600,"VenueDescription":"Fargo","IncidentNumber":"2011-00037706","Duration":"3495","Address":"1600 BLK 15 AVE N"},{"CFSID":-4702070,"AdditionalInfo":"","StreetPrefix":"","StreetPreType":"","StreetName":"MAIN","StreetType":"AVE","StreetSuffix":"","VenueName":"FGO","CallType":"Accident - Property","NatureOfCall":"1050/P","DateString":"10/13/2011 3:01:47 PM","Block":2300,"VenueDescription":"Fargo","IncidentNumber":"2011-00078306","Duration":"2954","Address":"2300 BLK MAIN AVE"},{"CFSID":-4702066,"AdditionalInfo":"","StreetPrefix":"","StreetPreType":"","StreetName":"13","StreetType":"AVE","StreetSuffix":"S","VenueName":"FGO","CallType":"Accident - Property","NatureOfCall":"10-50 P","DateString":"10/13/2011 2:53:50 PM","Block":4300,"VenueDescription":"Fargo","IncidentNumber":"2011-00078300","Duration":"2819","Address":"4300 BLK 13 AVE S"},{"CFSID":-4702063,"AdditionalInfo":"","StreetPrefix":"","StreetPreType":"","StreetName":"DAKOTA","StreetType":"DR","StreetSuffix":"N","VenueName":"FGO","CallType":"TC","NatureOfCall":"VEHICLE INSPECTION","DateString":"10/13/2011 2:47:16 PM","Block":1800,"VenueDescription":"Fargo","IncidentNumber":"","Duration":"296","Address":"1800 BLK DAKOTA DR N"},{"CFSID":-4702059,"AdditionalInfo":"","StreetPrefix":"","StreetPreType":"","StreetName":"7","StreetType":"AVE","StreetSuffix":"S","VenueName":"FGO","CallType":"Animal Calls","NatureOfCall":"PITBULL AT LARGE","DateString":"10/13/2011 2:41:30 PM","Block":0,"VenueDescription":"Fargo","IncidentNumber":"2011-00078299","Duration":"926","Address":" 7 AVE S"},{"CFSID":-4702053,"AdditionalInfo":"","StreetPrefix":"","StreetPreType":"","StreetName":"9","StreetType":"AVE","StreetSuffix":"S","VenueName":"FGO","CallType":"Impound","NatureOfCall":"IMPOUND","DateString":"10/13/2011 2:30:13 PM","Block":1300,"VenueDescription":"Fargo","IncidentNumber":"2011-00037705","Duration":"2256","Address":"1300 BLK 9 AVE S"},{"CFSID":-4702045,"AdditionalInfo":"","StreetPrefix":"","StreetPreType":"","StreetName":"45","StreetType":"ST","StreetSuffix":"S","VenueName":"FGO","CallType":"Accident - Property","NatureOfCall":"1050P","DateString":"10/13/2011 2:14:28 PM","Block":3100,"VenueDescription":"Fargo","IncidentNumber":"2011-00078294","Duration":"3329","Address":"3100 BLK 45 ST S"},{"CFSID":-4702043,"AdditionalInfo":"","StreetPrefix":"","StreetPreType":"","StreetName":"CENTENNIAL","StreetType":"BLVD","StreetSuffix":"N","VenueName":"FGO","CallType":"TC","NatureOfCall":"TRAFFIC COMPLAINT","DateString":"10/13/2011 2:11:53 PM","Block":0,"VenueDescription":"Fargo","IncidentNumber":"2011-00037704","Duration":"1092","Address":" CENTENNIAL BLVD N"},{"CFSID":-4702036,"AdditionalInfo":"","StreetPrefix":"","StreetPreType":"","StreetName":"11","StreetType":"ST","StreetSuffix":"S","VenueName":"FGO","CallType":"Animal Calls","NatureOfCall":"WELFARE CHECK ON DOG","DateString":"10/13/2011 2:06:38 PM","Block":200,"VenueDescription":"Fargo","IncidentNumber":"2011-00078295","Duration":"2167","Address":"200 BLK 11 ST S"},{"CFSID":-4702034,"AdditionalInfo":"","StreetPrefix":"","StreetPreType":"","StreetName":"20","StreetType":"ST","StreetSuffix":"S","VenueName":"FGO","CallType":"Accident - Property","NatureOfCall":"10-50 H&R","DateString":"10/13/2011 2:04:37 PM","Block":3200,"VenueDescription":"Fargo","IncidentNumber":"2011-00078296","Duration":"2918","Address":"3200 BLK 20 ST S"},{"CFSID":-4702033,"AdditionalInfo":"","StreetPrefix":"","StreetPreType":"","StreetName":"11","StreetType":"ST","StreetSuffix":"N","VenueName":"FGO","CallType":"Impaired Person","NatureOfCall":"1056/F  ASSIST SE","DateString":"10/13/2011 2:03:48 PM","Block":700,"VenueDescription":"Fargo","IncidentNumber":"Multiple incidents","Duration":"8017","Address":"700 BLK 11 ST N"},{"CFSID":-4702023,"AdditionalInfo":"","StreetPrefix":"","StreetPreType":"","StreetName":"2","StreetType":"AVE","StreetSuffix":"S","VenueName":"FGO","CallType":"Harassment","NatureOfCall":"HARASSMENT","DateString":"10/13/2011 1:53:23 PM","Block":1800,"VenueDescription":"Fargo","IncidentNumber":"2011-00078298","Duration":"5634","Address":"1800 BLK 2 AVE S"},{"CFSID":-4702022,"AdditionalInfo":"","StreetPrefix":"","StreetPreType":"","StreetName":"MAIN","StreetType":"AVE","StreetSuffix":"","VenueName":"FGO","CallType":"Accident - Property","NatureOfCall":"10-50 P","DateString":"10/13/2011 1:52:00 PM","Block":300,"VenueDescription":"Fargo","IncidentNumber":"2011-00078291","Duration":"2405","Address":"300 BLK MAIN AVE"},{"CFSID":-4702014,"AdditionalInfo":"","StreetPrefix":"","StreetPreType":"","StreetName":"15","StreetType":"AVE","StreetSuffix":"N","VenueName":"FGO","CallType":"Impound","NatureOfCall":"IMPOUND","DateString":"10/13/2011 1:38:37 PM","Block":1600,"VenueDescription":"Fargo","IncidentNumber":"2011-00037702","Duration":"1498","Address":"1600 BLK 15 AVE N"},{"CFSID":-4702009,"AdditionalInfo":"","StreetPrefix":"","StreetPreType":"","StreetName":"20","StreetType":"AVE","StreetSuffix":"S","VenueName":"FGO","CallType":"Accident - Property","NatureOfCall":"1050 H&R","DateString":"10/13/2011 1:32:57 PM","Block":2400,"VenueDescription":"Fargo","IncidentNumber":"2011-00078289","Duration":"5473","Address":"2400 BLK 20 AVE S"},{"CFSID":-4702004,"AdditionalInfo":"","StreetPrefix":"","StreetPreType":"","StreetName":"ADMINISTRATION","StreetType":"AVE","StreetSuffix":"N","VenueName":"FGO","CallType":"Impound","NatureOfCall":"IMPOUND","DateString":"10/13/2011 1:27:25 PM","Block":1400,"VenueDescription":"Fargo","IncidentNumber":"2011-00037703","Duration":"3511","Address":"1400 BLK ADMINISTRATION AVE N"},{"CFSID":-4701998,"AdditionalInfo":"","StreetPrefix":"","StreetPreType":"","StreetName":"38","StreetType":"ST","StreetSuffix":"S","VenueName":"FGO","CallType":"Accident - Property","NatureOfCall":"1050/P","DateString":"10/13/2011 1:19:19 PM","Block":1300,"VenueDescription":"Fargo","IncidentNumber":"2011-00078286","Duration":"1981","Address":"1300 BLK 38 ST S"},{"CFSID":-4701992,"AdditionalInfo":"","StreetPrefix":"","StreetPreType":"","StreetName":"17","StreetType":"ST","StreetSuffix":"S","VenueName":"FGO","CallType":"Commercial Fire","NatureOfCall":"CMF","DateString":"10/13/2011 1:15:43 PM","Block":2400,"VenueDescription":"Fargo","IncidentNumber":"2011-00032945","Duration":"563","Address":"2400 BLK 17 ST S"},{"CFSID":-4701991,"AdditionalInfo":"","StreetPrefix":"","StreetPreType":"","StreetName":"38","StreetType":"ST","StreetSuffix":"S","VenueName":"FGO","CallType":"Public Assist","NatureOfCall":"PUBLIC ASSIST","DateString":"10/13/2011 1:12:19 PM","Block":3700,"VenueDescription":"Fargo","IncidentNumber":"2011-00078287","Duration":"6047","Address":"3700 BLK 38 ST S"},{"CFSID":-4701990,"AdditionalInfo":"","StreetPrefix":"","StreetPreType":"","StreetName":"UNIVERSITY","StreetType":"DR","StreetSuffix":"N","VenueName":"FGO","CallType":"Impaired Person","NatureOfCall":"1056M LAYING IN FRONT ENTRY","DateString":"10/13/2011 1:10:58 PM","Block":700,"VenueDescription":"Fargo","IncidentNumber":"2011-00078283","Duration":"1239","Address":"700 BLK UNIVERSITY DR N"},{"CFSID":-4701979,"AdditionalInfo":"","StreetPrefix":"","StreetPreType":"","StreetName":"ADMINISTRATION","StreetType":"AVE","StreetSuffix":"N","VenueName":"FGO","CallType":"Impound","NatureOfCall":"IMPOUND","DateString":"10/13/2011 12:41:38 PM","Block":1400,"VenueDescription":"Fargo","IncidentNumber":"2011-00037701","Duration":"1748","Address":"1400 BLK ADMINISTRATION AVE N"},{"CFSID":-4701978,"AdditionalInfo":"","StreetPrefix":"","StreetPreType":"","StreetName":"ADMINISTRATION","StreetType":"AVE","StreetSuffix":"N","VenueName":"FGO","CallType":"Public Assist","NatureOfCall":"ESCORT","DateString":"10/13/2011 12:38:48 PM","Block":1300,"VenueDescription":"Fargo","IncidentNumber":"2011-00037700","Duration":"4936","Address":"1300 BLK ADMINISTRATION AVE N"},{"CFSID":-4701974,"AdditionalInfo":"","StreetPrefix":"","StreetPreType":"","StreetName":"UNIVERSITY","StreetType":"DR","StreetSuffix":"N","VenueName":"FGO","CallType":"Commercial Fire","NatureOfCall":"FIRE ALARM RESET","DateString":"10/13/2011 12:35:45 PM","Block":1800,"VenueDescription":"Fargo","IncidentNumber":"2011-00037699","Duration":"690","Address":"1800 BLK UNIVERSITY DR N"},{"CFSID":-4701973,"AdditionalInfo":"","StreetPrefix":"","StreetPreType":"","StreetName":"UNIVERSITY","StreetType":"DR","StreetSuffix":"N","VenueName":"FGO","CallType":"Commercial Fire Alarm Reset Only","NatureOfCall":"COMMERCIAL FIRE","DateString":"10/13/2011 12:33:37 PM","Block":1800,"VenueDescription":"Fargo","IncidentNumber":"2011-00032943","Duration":"839","Address":"1800 BLK UNIVERSITY DR N"},{"CFSID":-4701970,"AdditionalInfo":"","StreetPrefix":"","StreetPreType":"","StreetName":"6","StreetType":"AVE","StreetSuffix":"S","VenueName":"FGO","CallType":"Abuse","NatureOfCall":"CHILD ABUSE","DateString":"10/13/2011 12:29:35 PM","Block":2200,"VenueDescription":"Fargo","IncidentNumber":"2011-00078279","Duration":"4771","Address":"2200 BLK 6 AVE S"},{"CFSID":-4701968,"AdditionalInfo":"","StreetPrefix":"","StreetPreType":"","StreetName":"45","StreetType":"ST","StreetSuffix":"S","VenueName":"FGO","CallType":"Animal Calls","NatureOfCall":"FOUND DOG","DateString":"10/13/2011 12:19:02 PM","Block":0,"VenueDescription":"Fargo","IncidentNumber":"2011-00078278","Duration":"2701","Address":" 45 ST S"},{"CFSID":-4701967,"AdditionalInfo":"","StreetPrefix":"","StreetPreType":"","StreetName":"BROADWAY","StreetType":"","StreetSuffix":"N","VenueName":"FGO","CallType":"Vandalism","NatureOfCall":"BIKE RODE OVER NEW CONCRETE","DateString":"10/13/2011 12:14:00 PM","Block":1200,"VenueDescription":"Fargo","IncidentNumber":"2011-00078277","Duration":"1123","Address":"1200 BLK BROADWAY N"},{"CFSID":-4701965,"AdditionalInfo":"","StreetPrefix":"","StreetPreType":"","StreetName":"12","StreetType":"AVE","StreetSuffix":"S","VenueName":"FGO","CallType":"SU","NatureOfCall":"SUSP MALE IN VEH","DateString":"10/13/2011 12:10:54 PM","Block":1900,"VenueDescription":"Fargo","IncidentNumber":"2011-00078276","Duration":"951","Address":"1900 BLK 12 AVE S"},{"CFSID":-4701963,"AdditionalInfo":"","StreetPrefix":"","StreetPreType":"","StreetName":"10","StreetType":"ST","StreetSuffix":"N","VenueName":"FGO","CallType":"Commercial Fire Alarm Reset Only","NatureOfCall":"RESET ONLY","DateString":"10/13/2011 12:06:31 PM","Block":1700,"VenueDescription":"Fargo","IncidentNumber":"2011-00032942","Duration":"891","Address":"1700 BLK 10 ST N"},{"CFSID":-4701962,"AdditionalInfo":"","StreetPrefix":"","StreetPreType":"","StreetName":"10","StreetType":"ST","StreetSuffix":"N","VenueName":"FGO","CallType":"Commercial Fire","NatureOfCall":"FIRE ALARM","DateString":"10/13/2011 12:04:11 PM","Block":1700,"VenueDescription":"Fargo","IncidentNumber":"2011-00037698","Duration":"926","Address":"1700 BLK 10 ST N"},{"CFSID":-4701959,"AdditionalInfo":"","StreetPrefix":"","StreetPreType":"","StreetName":"12","StreetType":"AVE","StreetSuffix":"S","VenueName":"FGO","CallType":"Accident - Property","NatureOfCall":"1050 P - BLOCKING TRAFFIC","DateString":"10/13/2011 11:55:38 AM","Block":0,"VenueDescription":"Fargo","IncidentNumber":"2011-00078273","Duration":"2053","Address":" 12 AVE S"},{"CFSID":-4701954,"AdditionalInfo":"","StreetPrefix":"","StreetPreType":"","StreetName":"CENTENNIAL","StreetType":"BLVD","StreetSuffix":"N","VenueName":"FGO","CallType":"Building Check NDSU","NatureOfCall":"BUILDING CHECK","DateString":"10/13/2011 11:45:38 AM","Block":1300,"VenueDescription":"Fargo","IncidentNumber":"2011-00037696","Duration":"294","Address":"1300 BLK CENTENNIAL BLVD N"},{"CFSID":-4701953,"AdditionalInfo":"","StreetPrefix":"","StreetPreType":"","StreetName":"UNIVERSITY","StreetType":"DR","StreetSuffix":"S","VenueName":"FGO","CallType":"ATL Wanted","NatureOfCall":"ATL 1099/1021 COMP","DateString":"10/13/2011 11:44:24 AM","Block":1700,"VenueDescription":"Fargo","IncidentNumber":"2011-00078274","Duration":"8245","Address":"1700 BLK UNIVERSITY DR S"},{"CFSID":-4701952,"AdditionalInfo":"","StreetPrefix":"","StreetPreType":"","StreetName":"4","StreetType":"ST","StreetSuffix":"N","VenueName":"FGO","CallType":"Sexual Assault","NatureOfCall":"SEXUAL ASSAULT","DateString":"10/13/2011 11:43:53 AM","Block":200,"VenueDescription":"Fargo","IncidentNumber":"2011-00078271","Duration":"46","Address":"200 BLK 4 ST N"},{"CFSID":-4701951,"AdditionalInfo":"","StreetPrefix":"","StreetPreType":"","StreetName":"4","StreetType":"ST","StreetSuffix":"N","VenueName":"FGO","CallType":"Sexual Assault","NatureOfCall":"SEXUAL ASSAULT","DateString":"10/13/2011 11:43:01 AM","Block":200,"VenueDescription":"Fargo","IncidentNumber":"2011-00078270","Duration":"51","Address":"200 BLK 4 ST N"},{"CFSID":-4701950,"AdditionalInfo":"","StreetPrefix":"","StreetPreType":"","StreetName":"28","StreetType":"AVE","StreetSuffix":"N","VenueName":"FGO","CallType":"Animal Calls","NatureOfCall":"P/U CAT","DateString":"10/13/2011 11:42:27 AM","Block":1200,"VenueDescription":"Fargo","IncidentNumber":"2011-00078275","Duration":"4345","Address":"1200 BLK 28 AVE N"},{"CFSID":-4701946,"AdditionalInfo":"","StreetPrefix":"","StreetPreType":"","StreetName":"BROADWAY","StreetType":"","StreetSuffix":"N","VenueName":"FGO","CallType":"Threats","NatureOfCall":"THREATS/JUST HPND","DateString":"10/13/2011 11:37:58 AM","Block":0,"VenueDescription":"Fargo","IncidentNumber":"2011-00078267","Duration":"1558","Address":"0 BLK BROADWAY N"},{"CFSID":-4701943,"AdditionalInfo":"","StreetPrefix":"","StreetPreType":"","StreetName":"4","StreetType":"AVE","StreetSuffix":"N","VenueName":"FGO","CallType":"Impaired Person","NatureOfCall":"1056 PPL","DateString":"10/13/2011 11:23:22 AM","Block":200,"VenueDescription":"Fargo","IncidentNumber":"2011-00078265","Duration":"3942","Address":"200 BLK 4 AVE N"},{"CFSID":-4701940,"AdditionalInfo":"","StreetPrefix":"","StreetPreType":"","StreetName":"18","StreetType":"ST","StreetSuffix":"S","VenueName":"FGO","CallType":"Theft","NatureOfCall":"THEFT **10-21**","DateString":"10/13/2011 11:21:04 AM","Block":200,"VenueDescription":"Fargo","IncidentNumber":"2011-00078268","Duration":"1849","Address":"200 BLK 18 ST S"},{"CFSID":-4701939,"AdditionalInfo":"","StreetPrefix":"","StreetPreType":"","StreetName":"37","StreetType":"AVE","StreetSuffix":"S","VenueName":"FGO","CallType":"Mentally Impaired","NatureOfCall":"1096 F","DateString":"10/13/2011 11:19:11 AM","Block":4400,"VenueDescription":"Fargo","IncidentNumber":"Multiple incidents","Duration":"1429","Address":"4400 BLK 37 AVE S"},{"CFSID":-4701938,"AdditionalInfo":"","StreetPrefix":"","StreetPreType":"","StreetName":"BROADWAY","StreetType":"","StreetSuffix":"N","VenueName":"FGO","CallType":"Impaired Person","NatureOfCall":"1056/M","DateString":"10/13/2011 11:18:01 AM","Block":100,"VenueDescription":"Fargo","IncidentNumber":"2011-00078261","Duration":"1044","Address":"100 BLK BROADWAY N"},{"CFSID":-4701937,"AdditionalInfo":"","StreetPrefix":"","StreetPreType":"","StreetName":"MAIN","StreetType":"AVE","StreetSuffix":"","VenueName":"FGO","CallType":"Accident - Property","NatureOfCall":"10-50 P","DateString":"10/13/2011 11:17:44 AM","Block":2100,"VenueDescription":"Fargo","IncidentNumber":"2011-00078260","Duration":"1354","Address":"2100 BLK MAIN AVE"},{"CFSID":-4701936,"AdditionalInfo":"","StreetPrefix":"","StreetPreType":"","StreetName":"UNIVERSITY","StreetType":"DR","StreetSuffix":"S","VenueName":"FGO","CallType":"Accident - Property","NatureOfCall":"1050/P","DateString":"10/13/2011 11:09:52 AM","Block":1700,"VenueDescription":"Fargo","IncidentNumber":"2011-00078264","Duration":"1582","Address":"1700 BLK UNIVERSITY DR S"},{"CFSID":-4701930,"AdditionalInfo":"","StreetPrefix":"","StreetPreType":"","StreetName":"UNIVERSITY","StreetType":"DR","StreetSuffix":"N","VenueName":"FGO","CallType":"Impound","NatureOfCall":"IMPOUND","DateString":"10/13/2011 11:01:39 AM","Block":1700,"VenueDescription":"Fargo","IncidentNumber":"2011-00037695","Duration":"2635","Address":"1700 BLK UNIVERSITY DR N"},{"CFSID":-4701926,"AdditionalInfo":"","StreetPrefix":"","StreetPreType":"","StreetName":"18","StreetType":"ST","StreetSuffix":"S","VenueName":"FGO","CallType":"Parking Complaint","NatureOfCall":"ABANDONED VEHICLE","DateString":"10/13/2011 10:56:55 AM","Block":2400,"VenueDescription":"Fargo","IncidentNumber":"2011-00078256","Duration":"2559","Address":"2400 BLK 18 ST S"},{"CFSID":-4701922,"AdditionalInfo":"","StreetPrefix":"","StreetPreType":"","StreetName":"CENTENNIAL","StreetType":"BLVD","StreetSuffix":"N","VenueName":"FGO","CallType":"Impound","NatureOfCall":"IMPOUND VEHICLE","DateString":"10/13/2011 10:47:17 AM","Block":1300,"VenueDescription":"Fargo","IncidentNumber":"2011-00037694","Duration":"1851","Address":"1300 BLK CENTENNIAL BLVD N"},{"CFSID":-4701919,"AdditionalInfo":"","StreetPrefix":"","StreetPreType":"","StreetName":"COLLEGE","StreetType":"ST","StreetSuffix":"N","VenueName":"FGO","CallType":"Parking Complaint","NatureOfCall":"SIL PLYMOUTH BLOCKING DRIVEWAY\r\n","DateString":"10/13/2011 10:42:10 AM","Block":1100,"VenueDescription":"Fargo","IncidentNumber":"2011-00078255","Duration":"1290","Address":"1100 BLK COLLEGE ST N"},{"CFSID":-4701918,"AdditionalInfo":"","StreetPrefix":"","StreetPreType":"","StreetName":"16 1/2","StreetType":"ST","StreetSuffix":"S","VenueName":"FGO","CallType":"Theft","NatureOfCall":"THEFT OF TAX REFUND/**10-21**","DateString":"10/13/2011 10:39:53 AM","Block":1500,"VenueDescription":"Fargo","IncidentNumber":"2011-00078252","Duration":"2384","Address":"1500 BLK 16 1/2 ST S"},{"CFSID":-4701917,"AdditionalInfo":"","StreetPrefix":"","StreetPreType":"","StreetName":"16","StreetType":"AVE","StreetSuffix":"S","VenueName":"FGO","CallType":"Harassment","NatureOfCall":"HARASSMENT/1021","DateString":"10/13/2011 10:39:37 AM","Block":4700,"VenueDescription":"Fargo","IncidentNumber":"2011-00078253","Duration":"2080","Address":"4700 BLK 16 AVE S"},{"CFSID":-4701916,"AdditionalInfo":"","StreetPrefix":"","StreetPreType":"","StreetName":"32","StreetType":"ST","StreetSuffix":"S","VenueName":"FGO","CallType":"Domestic","NatureOfCall":"VERBAL DOMESTIC ","DateString":"10/13/2011 10:39:19 AM","Block":1300,"VenueDescription":"Fargo","IncidentNumber":"2011-00078251","Duration":"1727","Address":"1300 BLK 32 ST S"},{"CFSID":-4701915,"AdditionalInfo":"","StreetPrefix":"","StreetPreType":"","StreetName":"UNIVERSITY","StreetType":"DR","StreetSuffix":"S","VenueName":"FGO","CallType":"Accident - Property","NatureOfCall":"1050/P","DateString":"10/13/2011 10:37:51 AM","Block":1700,"VenueDescription":"Fargo","IncidentNumber":"","Duration":"83","Address":"1700 BLK UNIVERSITY DR S"},{"CFSID":-4701914,"AdditionalInfo":"","StreetPrefix":"","StreetPreType":"","StreetName":"45","StreetType":"ST","StreetSuffix":"S","VenueName":"FGO","CallType":"Theft","NatureOfCall":"TH OF SERVICES","DateString":"10/13/2011 10:37:28 AM","Block":1000,"VenueDescription":"Fargo","IncidentNumber":"2011-00078250","Duration":"1453","Address":"1000 BLK 45 ST S"},{"CFSID":-4701910,"AdditionalInfo":"","StreetPrefix":"","StreetPreType":"","StreetName":"UNIVERSITY","StreetType":"DR","StreetSuffix":"S","VenueName":"FGO","CallType":"Public Assist","NatureOfCall":"STRANDED F","DateString":"10/13/2011 10:25:42 AM","Block":1300,"VenueDescription":"Fargo","IncidentNumber":"2011-00078248","Duration":"1086","Address":"1300 BLK UNIVERSITY DR S"},{"CFSID":-4701903,"AdditionalInfo":"","StreetPrefix":"","StreetPreType":"","StreetName":"MAIN","StreetType":"AVE","StreetSuffix":"","VenueName":"FGO","CallType":"Theft","NatureOfCall":"THEFT RPT","DateString":"10/13/2011 10:14:08 AM","Block":2400,"VenueDescription":"Fargo","IncidentNumber":"2011-00078244","Duration":"1594","Address":"2400 BLK MAIN AVE"},{"CFSID":-4701901,"AdditionalInfo":"","StreetPrefix":"","StreetPreType":"","StreetName":"UNIVERSITY","StreetType":"DR","StreetSuffix":"S","VenueName":"FGO","CallType":"Commercial Fire","NatureOfCall":"C OMMERCIAL FIRE ALARMS","DateString":"10/13/2011 10:13:31 AM","Block":3500,"VenueDescription":"Fargo","IncidentNumber":"","Duration":"74","Address":"3500 BLK UNIVERSITY DR S"},{"CFSID":-4701898,"AdditionalInfo":"","StreetPrefix":"","StreetPreType":"","StreetName":"UNIVERSITY","StreetType":"DR","StreetSuffix":"S","VenueName":"FGO","CallType":"Commercial Fire","NatureOfCall":"CMF","DateString":"10/13/2011 10:07:00 AM","Block":3500,"VenueDescription":"Fargo","IncidentNumber":"2011-00032941","Duration":"1794","Address":"3500 BLK UNIVERSITY DR S"},{"CFSID":-4701890,"AdditionalInfo":"","StreetPrefix":"","StreetPreType":"","StreetName":"ROBERTS","StreetType":"ST","StreetSuffix":"N","VenueName":"FGO","CallType":"Mentally Impaired","NatureOfCall":"1096/M","DateString":"10/13/2011 9:56:37 AM","Block":100,"VenueDescription":"Fargo","IncidentNumber":"Multiple incidents","Duration":"2561","Address":"100 BLK ROBERTS ST N"},{"CFSID":-4701889,"AdditionalInfo":"","StreetPrefix":"","StreetPreType":"","StreetName":"30 1/2","StreetType":"AVE","StreetSuffix":"S","VenueName":"FGO","CallType":"Abuse","NatureOfCall":"CHILD ABUSE/1021","DateString":"10/13/2011 9:54:33 AM","Block":2400,"VenueDescription":"Fargo","IncidentNumber":"2011-00078249","Duration":"7145","Address":"2400 BLK 30 1/2 AVE S"},{"CFSID":-4701888,"AdditionalInfo":"","StreetPrefix":"","StreetPreType":"","StreetName":"2","StreetType":"AVE","StreetSuffix":"N","VenueName":"FGO","CallType":"Building Check NDSU","NatureOfCall":"BUILDING CHECK","DateString":"10/13/2011 9:54:04 AM","Block":700,"VenueDescription":"Fargo","IncidentNumber":"2011-00037693","Duration":"1475","Address":"700 BLK 2 AVE N"},{"CFSID":-4701887,"AdditionalInfo":"","StreetPrefix":"","StreetPreType":"","StreetName":"17","StreetType":"AVE","StreetSuffix":"N","VenueName":"FGO","CallType":"Public Assist","NatureOfCall":"ESCORT","DateString":"10/13/2011 9:52:39 AM","Block":1300,"VenueDescription":"Fargo","IncidentNumber":"2011-00037692","Duration":"1534","Address":"1300 BLK 17 AVE N"},{"CFSID":-4701880,"AdditionalInfo":"","StreetPrefix":"","StreetPreType":"","StreetName":"9","StreetType":"ST","StreetSuffix":"N","VenueName":"FGO","CallType":"Animal Calls","NatureOfCall":"P/U CAT","DateString":"10/13/2011 9:35:38 AM","Block":1200,"VenueDescription":"Fargo","IncidentNumber":"2011-00078240","Duration":"2615","Address":"1200 BLK 9 ST N"},{"CFSID":-4701876,"AdditionalInfo":"","StreetPrefix":"","StreetPreType":"","StreetName":"2","StreetType":"AVE","StreetSuffix":"N","VenueName":"FGO","CallType":"Building Check NDSU","NatureOfCall":"BUILDING CHECK","DateString":"10/13/2011 9:30:45 AM","Block":700,"VenueDescription":"Fargo","IncidentNumber":"2011-00037691","Duration":"1388","Address":"700 BLK 2 AVE N"},{"CFSID":-4701875,"AdditionalInfo":"","StreetPrefix":"","StreetPreType":"","StreetName":"14","StreetType":"ST","StreetSuffix":"N","VenueName":"FGO","CallType":"Vandalism","NatureOfCall":"VANDALISM TO HOUSE *1021*","DateString":"10/13/2011 9:30:39 AM","Block":800,"VenueDescription":"Fargo","IncidentNumber":"2011-00078238","Duration":"7991","Address":"800 BLK 14 ST N"},{"CFSID":-4701874,"AdditionalInfo":"","StreetPrefix":"","StreetPreType":"","StreetName":"TIMBERLINE","StreetType":"DR","StreetSuffix":"S","VenueName":"FGO","CallType":"Accident - Property","NatureOfCall":"1050 P RPT - HAPPN TUES","DateString":"10/13/2011 9:30:05 AM","Block":4300,"VenueDescription":"Fargo","IncidentNumber":"2011-00078239","Duration":"6168","Address":"4300 BLK TIMBERLINE DR S"},{"CFSID":-4701868,"AdditionalInfo":"","StreetPrefix":"","StreetPreType":"","StreetName":"UNIVERSITY","StreetType":"DR","StreetSuffix":"S","VenueName":"FGO","CallType":"Commercial Fire","NatureOfCall":"CMF","DateString":"10/13/2011 9:22:34 AM","Block":1500,"VenueDescription":"Fargo","IncidentNumber":"2011-00032940","Duration":"650","Address":"1500 BLK UNIVERSITY DR S"},{"CFSID":-4701867,"AdditionalInfo":"","StreetPrefix":"","StreetPreType":"","StreetName":"14 1/2","StreetType":"ST","StreetSuffix":"S","VenueName":"FGO","CallType":"Parking Complaint","NatureOfCall":"ABAN VEH","DateString":"10/13/2011 9:19:56 AM","Block":1300,"VenueDescription":"Fargo","IncidentNumber":"","Duration":"1111","Address":"1300 BLK 14 1/2 ST S"},{"CFSID":-4701864,"AdditionalInfo":"","StreetPrefix":"","StreetPreType":"","StreetName":"1","StreetType":"AVE","StreetSuffix":"N","VenueName":"FGO","CallType":"SU","NatureOfCall":"SUSP MALE","DateString":"10/13/2011 9:16:51 AM","Block":1400,"VenueDescription":"Fargo","IncidentNumber":"2011-00078234","Duration":"654","Address":"1400 BLK 1 AVE N"},{"CFSID":-4701861,"AdditionalInfo":"","StreetPrefix":"","StreetPreType":"","StreetName":"32","StreetType":"AVE","StreetSuffix":"N","VenueName":"FGO","CallType":"AC","NatureOfCall":"AIRPORT CHECK","DateString":"10/13/2011 9:10:52 AM","Block":2800,"VenueDescription":"Fargo","IncidentNumber":"2011-00078231","Duration":"613","Address":"2800 BLK 32 AVE N"},{"CFSID":-4701857,"AdditionalInfo":"","StreetPrefix":"","StreetPreType":"","StreetName":"NORTHERN PACIFIC","StreetType":"AVE","StreetSuffix":"N","VenueName":"FGO","CallType":"Building Check NDSU","NatureOfCall":"BUILDING CHECK","DateString":"10/13/2011 9:07:24 AM","Block":600,"VenueDescription":"Fargo","IncidentNumber":"2011-00037690","Duration":"1239","Address":"600 BLK NORTHERN PACIFIC AVE N"},{"CFSID":-4701840,"AdditionalInfo":"","StreetPrefix":"","StreetPreType":"","StreetName":"NORTHERN PACIFIC","StreetType":"AVE","StreetSuffix":"N","VenueName":"FGO","CallType":"Vandalism","NatureOfCall":"VAN TO PROP","DateString":"10/13/2011 8:43:11 AM","Block":1200,"VenueDescription":"Fargo","IncidentNumber":"2011-00078227","Duration":"2736","Address":"1200 BLK NORTHERN PACIFIC AVE N"},{"CFSID":-4701838,"AdditionalInfo":"","StreetPrefix":"","StreetPreType":"","StreetName":"3","StreetType":"AVE","StreetSuffix":"S","VenueName":"FGO","CallType":"Animal Calls","NatureOfCall":"BARKING DOG","DateString":"10/13/2011 8:37:12 AM","Block":1600,"VenueDescription":"Fargo","IncidentNumber":"2011-00078229","Duration":"2247","Address":"1600 BLK 3 AVE S"},{"CFSID":-4701827,"AdditionalInfo":"","StreetPrefix":"","StreetPreType":"","StreetName":"18","StreetType":"ST","StreetSuffix":"S","VenueName":"FGO","CallType":"Bicycle - Found","NatureOfCall":"P/U BI","DateString":"10/13/2011 8:16:13 AM","Block":2500,"VenueDescription":"Fargo","IncidentNumber":"2011-00078235","Duration":"5401","Address":"2500 BLK 18 ST S"},{"CFSID":-4701825,"AdditionalInfo":"","StreetPrefix":"","StreetPreType":"","StreetName":"OAKLAND","StreetType":"AVE","StreetSuffix":"S","VenueName":"FGO","CallType":"Fraud","NatureOfCall":"SCAM RPRT  **1021**","DateString":"10/13/2011 8:07:53 AM","Block":400,"VenueDescription":"Fargo","IncidentNumber":"2011-00078219","Duration":"1110","Address":"400 BLK OAKLAND AVE S"},{"CFSID":-4701824,"AdditionalInfo":"","StreetPrefix":"","StreetPreType":"","StreetName":"4","StreetType":"AVE","StreetSuffix":"S","VenueName":"FGO","CallType":"Parking Complaint","NatureOfCall":"UNATTACHED TRAILER","DateString":"10/13/2011 8:02:12 AM","Block":1300,"VenueDescription":"Fargo","IncidentNumber":"2011-00078221","Duration":"6836","Address":"1300 BLK 4 AVE S"},{"CFSID":-4701817,"AdditionalInfo":"","StreetPrefix":"","StreetPreType":"","StreetName":"2","StreetType":"ST","StreetSuffix":"S","VenueName":"FGO","CallType":"Impaired Person","NatureOfCall":"10-56/M PASSED OUT","DateString":"10/13/2011 7:51:14 AM","Block":100,"VenueDescription":"Fargo","IncidentNumber":"Multiple incidents","Duration":"995","Address":"100 BLK 2 ST S"},{"CFSID":-4701808,"AdditionalInfo":"","StreetPrefix":"","StreetPreType":"","StreetName":"UNIVERSITY","StreetType":"DR","StreetSuffix":"S","VenueName":"FGO","CallType":"Public Assist","NatureOfCall":"ASSIST FEMALE","DateString":"10/13/2011 7:22:15 AM","Block":2700,"VenueDescription":"Fargo","IncidentNumber":"2011-00078212","Duration":"7610","Address":"2700 BLK UNIVERSITY DR S"},{"CFSID":-4701798,"AdditionalInfo":"","StreetPrefix":"","StreetPreType":"","StreetName":"MAIN","StreetType":"AVE","StreetSuffix":"","VenueName":"FGO","CallType":"Accident - Injury","NatureOfCall":"1050I","DateString":"10/13/2011 6:27:00 AM","Block":300,"VenueDescription":"Fargo","IncidentNumber":"Multiple incidents","Duration":"2316","Address":"300 BLK MAIN AVE"},{"CFSID":-4701789,"AdditionalInfo":"","StreetPrefix":"","StreetPreType":"","StreetName":"36","StreetType":"AVE","StreetSuffix":"N","VenueName":"FGO","CallType":"Impaired Person","NatureOfCall":"UNWANTED 1056 SON","DateString":"10/13/2011 5:30:50 AM","Block":1000,"VenueDescription":"Fargo","IncidentNumber":"2011-00078206","Duration":"3101","Address":"1000 BLK 36 AVE N"},{"CFSID":-4701784,"AdditionalInfo":"","StreetPrefix":"","StreetPreType":"","StreetName":"13","StreetType":"AVE","StreetSuffix":"S","VenueName":"FGO","CallType":"Alarm","NatureOfCall":"1090","DateString":"10/13/2011 4:25:07 AM","Block":3900,"VenueDescription":"Fargo","IncidentNumber":"2011-00078204","Duration":"1534","Address":"3900 BLK 13 AVE S"},{"CFSID":-4701783,"AdditionalInfo":"","StreetPrefix":"","StreetPreType":"","StreetName":"36","StreetType":"AVE","StreetSuffix":"N","VenueName":"FGO","CallType":"Disturbance","NatureOfCall":"UNKNOWN PROBLEM","DateString":"10/13/2011 4:11:55 AM","Block":1000,"VenueDescription":"Fargo","IncidentNumber":"Multiple incidents","Duration":"7061","Address":"1000 BLK 36 AVE N"},{"CFSID":-4701780,"AdditionalInfo":"","StreetPrefix":"","StreetPreType":"","StreetName":"LILAC","StreetType":"LN","StreetSuffix":"N","VenueName":"FGO","CallType":"Burglary","NatureOfCall":"BURGLARY IN PROGRESS","DateString":"10/13/2011 4:08:08 AM","Block":2700,"VenueDescription":"Fargo","IncidentNumber":"2011-00078202","Duration":"1261","Address":"2700 BLK LILAC LN N"},{"CFSID":-4701778,"AdditionalInfo":"","StreetPrefix":"","StreetPreType":"","StreetName":"UNIVERSITY","StreetType":"DR","StreetSuffix":"N","VenueName":"FGO","CallType":"Vandalism","NatureOfCall":"HIS CAR WINDOW IS BROKE","DateString":"10/13/2011 3:39:02 AM","Block":1700,"VenueDescription":"Fargo","IncidentNumber":"2011-00037688","Duration":"2514","Address":"1700 BLK UNIVERSITY DR N"},{"CFSID":-4701776,"AdditionalInfo":"","StreetPrefix":"","StreetPreType":"","StreetName":"16","StreetType":"AVE","StreetSuffix":"S","VenueName":"FGO","CallType":"SU","NatureOfCall":"SUSP PEOPLE","DateString":"10/13/2011 3:35:56 AM","Block":3200,"VenueDescription":"Fargo","IncidentNumber":"2011-00078200","Duration":"978","Address":"3200 BLK 16 AVE S"},{"CFSID":-4701774,"AdditionalInfo":"","StreetPrefix":"","StreetPreType":"","StreetName":"32","StreetType":"AVE","StreetSuffix":"S","VenueName":"FGO","CallType":"Impaired Person","NatureOfCall":"1056 M NEEDS DETOX / ESSENTIA","DateString":"10/13/2011 3:23:08 AM","Block":3000,"VenueDescription":"Fargo","IncidentNumber":"2011-00078199","Duration":"1771","Address":"3000 BLK 32 AVE S"},{"CFSID":-4701771,"AdditionalInfo":"","StreetPrefix":"","StreetPreType":"","StreetName":"22","StreetType":"ST","StreetSuffix":"S","VenueName":"FGO","CallType":"Loud Party/People","NatureOfCall":"LOUD PEOPLE","DateString":"10/13/2011 3:02:20 AM","Block":1100,"VenueDescription":"Fargo","IncidentNumber":"2011-00078197","Duration":"840","Address":"1100 BLK 22 ST S"},{"CFSID":-4701766,"AdditionalInfo":"","StreetPrefix":"","StreetPreType":"","StreetName":"ALBRECHT","StreetType":"BLVD","StreetSuffix":"N","VenueName":"FGO","CallType":"Alarm","NatureOfCall":"DOOR PROPPED ALARM","DateString":"10/13/2011 2:46:26 AM","Block":1400,"VenueDescription":"Fargo","IncidentNumber":"2011-00037687","Duration":"1520","Address":"1400 BLK ALBRECHT BLVD N"},{"CFSID":-4701765,"AdditionalInfo":"","StreetPrefix":"","StreetPreType":"","StreetName":"12","StreetType":"ST","StreetSuffix":"N","VenueName":"FGO","CallType":"SU","NatureOfCall":"2 SUSP M","DateString":"10/13/2011 2:43:05 AM","Block":1200,"VenueDescription":"Fargo","IncidentNumber":"2011-00078195","Duration":"909","Address":"1200 BLK 12 ST N"},{"CFSID":-4701764,"AdditionalInfo":"","StreetPrefix":"","StreetPreType":"","StreetName":"18","StreetType":"ST","StreetSuffix":"N","VenueName":"FGO","CallType":"Alarm","NatureOfCall":"DOOR PROPPED ALARM","DateString":"10/13/2011 2:42:24 AM","Block":1400,"VenueDescription":"Fargo","IncidentNumber":"2011-00037686","Duration":"1548","Address":"1400 BLK 18 ST N"},{"CFSID":-4701755,"AdditionalInfo":"","StreetPrefix":"","StreetPreType":"","StreetName":"BROADWAY","StreetType":"","StreetSuffix":"N","VenueName":"FGO","CallType":"Disturbance","NatureOfCall":"FIGHT / FORT KNOX","DateString":"10/13/2011 1:49:12 AM","Block":0,"VenueDescription":"Fargo","IncidentNumber":"2011-00078189","Duration":"847","Address":"0 BLK BROADWAY N"},{"CFSID":-4701748,"AdditionalInfo":"","StreetPrefix":"","StreetPreType":"","StreetName":"34","StreetType":"ST","StreetSuffix":"S","VenueName":"FGO","CallType":"Missing Person","NatureOfCall":"13YOA F","DateString":"10/13/2011 1:28:36 AM","Block":3000,"VenueDescription":"Fargo","IncidentNumber":"2011-00078188","Duration":"2405","Address":"3000 BLK 34 ST S"},{"CFSID":-4701747,"AdditionalInfo":"","StreetPrefix":"","StreetPreType":"","StreetName":"45","StreetType":"ST","StreetSuffix":"S","VenueName":"FGO","CallType":"Impaired Driver","NatureOfCall":"1055","DateString":"10/13/2011 1:23:09 AM","Block":1700,"VenueDescription":"Fargo","IncidentNumber":"2011-00078186","Duration":"279","Address":"1700 BLK 45 ST S"},{"CFSID":-4701744,"AdditionalInfo":"","StreetPrefix":"","StreetPreType":"","StreetName":"1","StreetType":"AVE","StreetSuffix":"S","VenueName":"FGO","CallType":"Impaired Person","NatureOfCall":"WELFARE CHECK ON 1056 F","DateString":"10/13/2011 1:13:20 AM","Block":1500,"VenueDescription":"Fargo","IncidentNumber":"2011-00078185","Duration":"779","Address":"1500 BLK 1 AVE S"},{"CFSID":-4701743,"AdditionalInfo":"","StreetPrefix":"","StreetPreType":"","StreetName":"19","StreetType":"ST","StreetSuffix":"S","VenueName":"FGO","CallType":"Impaired Driver","NatureOfCall":"1055","DateString":"10/13/2011 1:10:47 AM","Block":0,"VenueDescription":"Fargo","IncidentNumber":"2011-00078184","Duration":"4838","Address":" 19 ST S"},{"CFSID":-4701735,"AdditionalInfo":"","StreetPrefix":"","StreetPreType":"","StreetName":"16","StreetType":"AVE","StreetSuffix":"S","VenueName":"FGO","CallType":"Harassment","NatureOfCall":"NEIGHBOR COMPLAINT","DateString":"10/13/2011 12:43:21 AM","Block":5000,"VenueDescription":"Fargo","IncidentNumber":"","Duration":"253","Address":"5000 BLK 16 AVE S"},{"CFSID":-4701733,"AdditionalInfo":"","StreetPrefix":"","StreetPreType":"","StreetName":"16","StreetType":"AVE","StreetSuffix":"S","VenueName":"FGO","CallType":"Harassment","NatureOfCall":"HARASSMENT BY NEIGHBOR","DateString":"10/13/2011 12:38:24 AM","Block":5000,"VenueDescription":"Fargo","IncidentNumber":"2011-00078182","Duration":"2119","Address":"5000 BLK 16 AVE S"},{"CFSID":-4701731,"AdditionalInfo":"","StreetPrefix":"","StreetPreType":"","StreetName":"17","StreetType":"AVE","StreetSuffix":"S","VenueName":"FGO","CallType":"Impaired Person","NatureOfCall":"1056 M","DateString":"10/13/2011 12:36:35 AM","Block":4300,"VenueDescription":"Fargo","IncidentNumber":"2011-00078179","Duration":"1776","Address":"4300 BLK 17 AVE S"},{"CFSID":-4701721,"AdditionalInfo":"","StreetPrefix":"","StreetPreType":"","StreetName":"49","StreetType":"ST","StreetSuffix":"S","VenueName":"FGO","CallType":"Harassment","NatureOfCall":"NEIGHBOR SPRAYING LIQUID ON CALLER","DateString":"10/13/2011 12:12:23 AM","Block":1700,"VenueDescription":"Fargo","IncidentNumber":"2011-00078177","Duration":"2757","Address":"1700 BLK 49 ST S"}]}